[{"FREDERICK":"FALSE","GETTYSBURG":"TRUE","LEMOYNE":"TRUE","YORK":"TRUE","brand":"AIR FACTORY","flavor":"Creamy Crunch","juiceID":1},{"FREDERICK":"FALSE","GETTYSBURG":"FALSE","LEMOYNE":"TRUE","YORK":"TRUE","brand":"AIR FACTORY","flavor":"Mango Ice","juiceID":2},{"FREDERICK":"FALSE","GETTYSBURG":"TRUE","LEMOYNE":"TRUE","YORK":"TRUE","brand":"AIR FACTORY","flavor":"Melon Lush","juiceID":3},{"FREDERICK":"FALSE","GETTYSBURG":"FALSE","LEMOYNE":"TRUE","YORK":"TRUE","brand":"AIR FACTORY","flavor":"Melon Lush Ice","juiceID":4},{"FREDERICK":"FALSE","GETTYSBURG":"TRUE","LEMOYNE":"TRUE","YORK":"TRUE","brand":"AIR FACTORY","flavor":"Mint","juiceID":5},{"FREDERICK":"TRUE","GETTYSBURG":"FALSE","LEMOYNE":"TRUE","YORK":"TRUE","brand":"AIR FACTORY","flavor":"Mixed Berry","juiceID":6},{"FREDERICK":"FALSE","GETTYSBURG":"FALSE","LEMOYNE":"TRUE","YORK":"FALSE","brand":"AIR FACTORY","flavor":"Tropic Freeze","juiceID":7},{"FREDERICK":"TRUE","GETTYSBURG":"TRUE","LEMOYNE":"TRUE","YORK":"FALSE","brand":"AQUA","flavor":"Flow","juiceID":8},{"FREDERICK":"TRUE","GETTYSBURG":"TRUE","LEMOYNE":"TRUE","YORK":"FALSE","brand":"AQUA","flavor":"Oasis","juiceID":9},{"FREDERICK":"TRUE","GETTYSBURG":"TRUE","LEMOYNE":"TRUE","YORK":"FALSE","brand":"AQUA","flavor":"Pure","juiceID":10},{"FREDERICK":"TRUE","GETTYSBURG":"TRUE","LEMOYNE":"TRUE","YORK":"TRUE","brand":"BIG BOTTLE COMPANY","flavor":"Blueberry Cake","juiceID":11},{"FREDERICK":"TRUE","GETTYSBURG":"TRUE","LEMOYNE":"TRUE","YORK":"FALSE","brand":"BIG BOTTLE COMPANY","flavor":"Carnival Apple","juiceID":12},{"FREDERICK":"TRUE","GETTYSBURG":"TRUE","LEMOYNE":"TRUE","YORK":"FALSE","brand":"BIG BOTTLE COMPANY","flavor":"Chilled Mango","juiceID":13},{"FREDERICK":"TRUE","GETTYSBURG":"FALSE","LEMOYNE":"TRUE","YORK":"FALSE","brand":"BIG BOTTLE COMPANY","flavor":"Cinnamon Cream","juiceID":14},{"FREDERICK":"TRUE","GETTYSBURG":"TRUE","LEMOYNE":"TRUE","YORK":"TRUE","brand":"BIG BOTTLE COMPANY","flavor":"Jelly Donut","juiceID":15},{"FREDERICK":"TRUE","GETTYSBURG":"TRUE","LEMOYNE":"TRUE","YORK":"TRUE","brand":"BIG BOTTLE COMPANY","flavor":"Strawberry Milk","juiceID":16},{"FREDERICK":"TRUE","GETTYSBURG":"TRUE","LEMOYNE":"TRUE","YORK":"FALSE","brand":"BIG BOTTLE COMPANY","flavor":"Wildberry Limeade","juiceID":17},{"FREDERICK":"TRUE","GETTYSBURG":"TRUE","LEMOYNE":"TRUE","YORK":"FALSE","brand":"BIG F'N DEAL","flavor":"CRSP","juiceID":18},{"FREDERICK":"FALSE","GETTYSBURG":"TRUE","LEMOYNE":"TRUE","YORK":"FALSE","brand":"BIG F'N DEAL","flavor":"Tigers Blood","juiceID":19},{"FREDERICK":"TRUE","GETTYSBURG":"FALSE","LEMOYNE":"TRUE","YORK":"FALSE","brand":"BREWED AWAKENING","flavor":"Apple Cider","juiceID":20},{"FREDERICK":"TRUE","GETTYSBURG":"FALSE","LEMOYNE":"TRUE","YORK":"FALSE","brand":"BREWED AWAKENING","flavor":"Chai Tea","juiceID":21},{"FREDERICK":"TRUE","GETTYSBURG":"FALSE","LEMOYNE":"TRUE","YORK":"TRUE","brand":"BREWED AWAKENING","flavor":"Classic","juiceID":22},{"FREDERICK":"TRUE","GETTYSBURG":"FALSE","LEMOYNE":"TRUE","YORK":"TRUE","brand":"BREWED AWAKENING","flavor":"Pumpkin Spice","juiceID":23},{"FREDERICK":"FALSE","GETTYSBURG":"FALSE","LEMOYNE":"TRUE","YORK":"FALSE","brand":"CANDY KING","flavor":"Dweebz","juiceID":24},{"FREDERICK":"FALSE","GETTYSBURG":"FALSE","LEMOYNE":"TRUE","YORK":"FALSE","brand":"CANDY KINGBC","flavor":"Batch","juiceID":25},{"FREDERICK":"FALSE","GETTYSBURG":"FALSE","LEMOYNE":"TRUE","YORK":"FALSE","brand":"CANDY KINGBC","flavor":"Belts Strawberry","juiceID":26},{"FREDERICK":"FALSE","GETTYSBURG":"FALSE","LEMOYNE":"TRUE","YORK":"FALSE","brand":"CANDY KINGBC","flavor":"Dweebz","juiceID":27},{"FREDERICK":"FALSE","GETTYSBURG":"FALSE","LEMOYNE":"TRUE","YORK":"FALSE","brand":"CANDY KINGBC","flavor":"Grapefruit Gust","juiceID":28},{"FREDERICK":"FALSE","GETTYSBURG":"FALSE","LEMOYNE":"TRUE","YORK":"FALSE","brand":"CANDY KINGBC","flavor":"Lemon Drop","juiceID":29},{"FREDERICK":"FALSE","GETTYSBURG":"FALSE","LEMOYNE":"TRUE","YORK":"FALSE","brand":"CANDY KINGBC","flavor":"Melon Bubble Gum","juiceID":30},{"FREDERICK":"FALSE","GETTYSBURG":"FALSE","LEMOYNE":"TRUE","YORK":"FALSE","brand":"CANDY KINGBC","flavor":"Pink Lemonade Bubble Gum","juiceID":31},{"FREDERICK":"FALSE","GETTYSBURG":"FALSE","LEMOYNE":"TRUE","YORK":"FALSE","brand":"CANDY KINGBC","flavor":"Pink Squares","juiceID":32},{"FREDERICK":"FALSE","GETTYSBURG":"FALSE","LEMOYNE":"TRUE","YORK":"FALSE","brand":"CANDY KINGBC","flavor":"Strawberry Watermelon Bubble Gum","juiceID":33},{"FREDERICK":"FALSE","GETTYSBURG":"FALSE","LEMOYNE":"TRUE","YORK":"FALSE","brand":"CANDY KINGBC","flavor":"Swedish","juiceID":34},{"FREDERICK":"FALSE","GETTYSBURG":"FALSE","LEMOYNE":"TRUE","YORK":"FALSE","brand":"CANDY KINGBC","flavor":"Tropic Bubblegum","juiceID":35},{"FREDERICK":"FALSE","GETTYSBURG":"FALSE","LEMOYNE":"TRUE","YORK":"FALSE","brand":"CANDY KINGBC","flavor":"Worms","juiceID":36},{"FREDERICK":"FALSE","GETTYSBURG":"TRUE","LEMOYNE":"TRUE","YORK":"TRUE","brand":"CASSADAGA","flavor":"Cannoli Be Breakfast","juiceID":37},{"FREDERICK":"FALSE","GETTYSBURG":"FALSE","LEMOYNE":"TRUE","YORK":"TRUE","brand":"CASSADAGA","flavor":"Cannoli Be Cookie","juiceID":38},{"FREDERICK":"FALSE","GETTYSBURG":"TRUE","LEMOYNE":"TRUE","YORK":"TRUE","brand":"CASSADAGA","flavor":"Cannoli Be Graham","juiceID":39},{"FREDERICK":"FALSE","GETTYSBURG":"TRUE","LEMOYNE":"TRUE","YORK":"TRUE","brand":"CASSADAGA","flavor":"Cannoli Be Mine","juiceID":40},{"FREDERICK":"FALSE","GETTYSBURG":"TRUE","LEMOYNE":"TRUE","YORK":"FALSE","brand":"CASSADAGA","flavor":"Cannoli Be Nuts","juiceID":41},{"FREDERICK":"FALSE","GETTYSBURG":"TRUE","LEMOYNE":"TRUE","YORK":"TRUE","brand":"CASSADAGA","flavor":"Cannoli Be One","juiceID":42},{"FREDERICK":"FALSE","GETTYSBURG":"TRUE","LEMOYNE":"TRUE","YORK":"TRUE","brand":"CHARLIE NOBLE","flavor":"Charlie's Custard","juiceID":43},{"FREDERICK":"TRUE","GETTYSBURG":"TRUE","LEMOYNE":"TRUE","YORK":"TRUE","brand":"CHARLIE NOBLE","flavor":"Pistachio RY4","juiceID":44},{"FREDERICK":"FALSE","GETTYSBURG":"TRUE","LEMOYNE":"TRUE","YORK":"FALSE","brand":"CHARLIE NOBLE","flavor":"Shellback Slush","juiceID":45},{"FREDERICK":"TRUE","GETTYSBURG":"TRUE","LEMOYNE":"TRUE","YORK":"TRUE","brand":"CHARLIE NOBLE","flavor":"Tripoli","juiceID":46},{"FREDERICK":"FALSE","GETTYSBURG":"FALSE","LEMOYNE":"TRUE","YORK":"FALSE","brand":"CHARLIE NOBLE 120","flavor":"Cucumber Lime","juiceID":47},{"FREDERICK":"FALSE","GETTYSBURG":"FALSE","LEMOYNE":"TRUE","YORK":"FALSE","brand":"CHARLIE NOBLE 120","flavor":"Spiced Mango","juiceID":48},{"FREDERICK":"TRUE","GETTYSBURG":"FALSE","LEMOYNE":"TRUE","YORK":"TRUE","brand":"CHUBBY BUBBLE","flavor":"Purp","juiceID":49},{"FREDERICK":"TRUE","GETTYSBURG":"TRUE","LEMOYNE":"TRUE","YORK":"TRUE","brand":"CLOUD NURDZ","flavor":"Grape Apple","juiceID":50},{"FREDERICK":"TRUE","GETTYSBURG":"FALSE","LEMOYNE":"TRUE","YORK":"TRUE","brand":"CLOUD NURDZ","flavor":"Grape Strawberry","juiceID":51},{"FREDERICK":"FALSE","GETTYSBURG":"TRUE","LEMOYNE":"TRUE","YORK":"TRUE","brand":"CLOUD NURDZ","flavor":"Kiwi Melon","juiceID":52},{"FREDERICK":"TRUE","GETTYSBURG":"TRUE","LEMOYNE":"TRUE","YORK":"TRUE","brand":"CLOUD NURDZ","flavor":"Peach Blue Razz","juiceID":53},{"FREDERICK":"TRUE","GETTYSBURG":"TRUE","LEMOYNE":"TRUE","YORK":"TRUE","brand":"CLOUD NURDZ","flavor":"Watermelon Apple","juiceID":54},{"FREDERICK":"TRUE","GETTYSBURG":"FALSE","LEMOYNE":"TRUE","YORK":"TRUE","brand":"COASTAL CLOUDS","flavor":"Apple Peach Strawberry","juiceID":55},{"FREDERICK":"TRUE","GETTYSBURG":"TRUE","LEMOYNE":"TRUE","YORK":"TRUE","brand":"COASTAL CLOUDS","flavor":"Blood Orange Mango","juiceID":56},{"FREDERICK":"TRUE","GETTYSBURG":"TRUE","LEMOYNE":"TRUE","YORK":"TRUE","brand":"COASTAL CLOUDS","flavor":"Blueberry Banana","juiceID":57},{"FREDERICK":"FALSE","GETTYSBURG":"FALSE","LEMOYNE":"TRUE","YORK":"TRUE","brand":"COASTAL CLOUDS","flavor":"Blueberry Limeade","juiceID":58},{"FREDERICK":"FALSE","GETTYSBURG":"FALSE","LEMOYNE":"TRUE","YORK":"TRUE","brand":"COASTAL CLOUDS","flavor":"Chilled Apple Pear","juiceID":59},{"FREDERICK":"TRUE","GETTYSBURG":"FALSE","LEMOYNE":"TRUE","YORK":"FALSE","brand":"COASTAL CLOUDS","flavor":"Citrus Peach","juiceID":60},{"FREDERICK":"TRUE","GETTYSBURG":"FALSE","LEMOYNE":"TRUE","YORK":"TRUE","brand":"COASTAL CLOUDS","flavor":"Iced Apple Peach Strawberry","juiceID":61},{"FREDERICK":"FALSE","GETTYSBURG":"TRUE","LEMOYNE":"TRUE","YORK":"TRUE","brand":"COASTAL CLOUDS","flavor":"Iced Blood Orange Mango","juiceID":62},{"FREDERICK":"TRUE","GETTYSBURG":"FALSE","LEMOYNE":"TRUE","YORK":"TRUE","brand":"COASTAL CLOUDS","flavor":"Iced Mango Berries","juiceID":63},{"FREDERICK":"TRUE","GETTYSBURG":"TRUE","LEMOYNE":"TRUE","YORK":"TRUE","brand":"COASTAL CLOUDS","flavor":"Lemon Meringue","juiceID":64},{"FREDERICK":"FALSE","GETTYSBURG":"FALSE","LEMOYNE":"TRUE","YORK":"TRUE","brand":"COASTAL CLOUDS","flavor":"Lemon Raspberry","juiceID":65},{"FREDERICK":"TRUE","GETTYSBURG":"FALSE","LEMOYNE":"TRUE","YORK":"TRUE","brand":"COASTAL CLOUDS","flavor":"Mango","juiceID":66},{"FREDERICK":"TRUE","GETTYSBURG":"TRUE","LEMOYNE":"TRUE","YORK":"TRUE","brand":"COASTAL CLOUDS","flavor":"Maple Butter","juiceID":67},{"FREDERICK":"FALSE","GETTYSBURG":"FALSE","LEMOYNE":"TRUE","YORK":"TRUE","brand":"COASTAL CLOUDS","flavor":"Melon Berries","juiceID":68},{"FREDERICK":"TRUE","GETTYSBURG":"TRUE","LEMOYNE":"TRUE","YORK":"TRUE","brand":"COASTAL CLOUDS","flavor":"Menthol","juiceID":69},{"FREDERICK":"TRUE","GETTYSBURG":"TRUE","LEMOYNE":"TRUE","YORK":"FALSE","brand":"COASTAL CLOUDS","flavor":"Peach Tea","juiceID":70},{"FREDERICK":"TRUE","GETTYSBURG":"TRUE","LEMOYNE":"TRUE","YORK":"TRUE","brand":"COASTAL CLOUDS","flavor":"Strawberry Cream","juiceID":71},{"FREDERICK":"TRUE","GETTYSBURG":"TRUE","LEMOYNE":"TRUE","YORK":"TRUE","brand":"COASTAL CLOUDS","flavor":"Strawberry Pineapple Coconut","juiceID":72},{"FREDERICK":"TRUE","GETTYSBURG":"TRUE","LEMOYNE":"TRUE","YORK":"FALSE","brand":"COASTAL CLOUDS","flavor":"Tobacco","juiceID":73},{"FREDERICK":"TRUE","GETTYSBURG":"TRUE","LEMOYNE":"TRUE","YORK":"TRUE","brand":"COASTAL CLOUDS","flavor":"Tres Leches","juiceID":74},{"FREDERICK":"TRUE","GETTYSBURG":"TRUE","LEMOYNE":"TRUE","YORK":"FALSE","brand":"COASTAL CLOUDS","flavor":"Tropical Lemonade","juiceID":75},{"FREDERICK":"TRUE","GETTYSBURG":"TRUE","LEMOYNE":"TRUE","YORK":"TRUE","brand":"COASTAL CLOUDS","flavor":"Watermelon Cream","juiceID":76},{"FREDERICK":"FALSE","GETTYSBURG":"FALSE","LEMOYNE":"TRUE","YORK":"TRUE","brand":"CUSTARD MONSTER","flavor":"Blackberry","juiceID":77},{"FREDERICK":"TRUE","GETTYSBURG":"TRUE","LEMOYNE":"TRUE","YORK":"TRUE","brand":"CUSTARD MONSTER","flavor":"Blueberry","juiceID":78},{"FREDERICK":"TRUE","GETTYSBURG":"TRUE","LEMOYNE":"TRUE","YORK":"TRUE","brand":"CUSTARD MONSTER","flavor":"Butterscotch","juiceID":79},{"FREDERICK":"TRUE","GETTYSBURG":"TRUE","LEMOYNE":"TRUE","YORK":"TRUE","brand":"CUSTARD MONSTER","flavor":"Strawberry","juiceID":80},{"FREDERICK":"TRUE","GETTYSBURG":"TRUE","LEMOYNE":"TRUE","YORK":"TRUE","brand":"CUSTARD MONSTER","flavor":"Vanilla","juiceID":81},{"FREDERICK":"TRUE","GETTYSBURG":"FALSE","LEMOYNE":"TRUE","YORK":"FALSE","brand":"CYCLOPS VAPOR","flavor":"Colossus","juiceID":82},{"FREDERICK":"TRUE","GETTYSBURG":"FALSE","LEMOYNE":"TRUE","YORK":"FALSE","brand":"CYCLOPS VAPOR","flavor":"Hades","juiceID":83},{"FREDERICK":"TRUE","GETTYSBURG":"TRUE","LEMOYNE":"TRUE","YORK":"TRUE","brand":"DINNER LADY","flavor":"Lemon Tart","juiceID":84},{"FREDERICK":"FALSE","GETTYSBURG":"FALSE","LEMOYNE":"TRUE","YORK":"FALSE","brand":"EXCISION","flavor":"Paradox","juiceID":85},{"FREDERICK":"FALSE","GETTYSBURG":"FALSE","LEMOYNE":"TRUE","YORK":"FALSE","brand":"EXCISION","flavor":"Paradox on the Rocks","juiceID":86},{"FREDERICK":"FALSE","GETTYSBURG":"FALSE","LEMOYNE":"TRUE","YORK":"FALSE","brand":"EXCISION","flavor":"Robokitty Cream","juiceID":87},{"FREDERICK":"TRUE","GETTYSBURG":"TRUE","LEMOYNE":"TRUE","YORK":"TRUE","brand":"FERRUM CITY","flavor":"Angry Fried Banana","juiceID":88},{"FREDERICK":"TRUE","GETTYSBURG":"TRUE","LEMOYNE":"TRUE","YORK":"TRUE","brand":"FERRUM CITY","flavor":"Angry Graham Bear","juiceID":89},{"FREDERICK":"TRUE","GETTYSBURG":"FALSE","LEMOYNE":"TRUE","YORK":"TRUE","brand":"FERRUM CITY","flavor":"Angry Pink Lemonade","juiceID":90},{"FREDERICK":"TRUE","GETTYSBURG":"FALSE","LEMOYNE":"TRUE","YORK":"TRUE","brand":"FERRUM CITY","flavor":"Bloo Berry","juiceID":91},{"FREDERICK":"FALSE","GETTYSBURG":"TRUE","LEMOYNE":"TRUE","YORK":"TRUE","brand":"FERRUM CITY","flavor":"Blue Fish","juiceID":92},{"FREDERICK":"TRUE","GETTYSBURG":"TRUE","LEMOYNE":"TRUE","YORK":"TRUE","brand":"FERRUM CITY","flavor":"Cereal 11","juiceID":93},{"FREDERICK":"FALSE","GETTYSBURG":"FALSE","LEMOYNE":"TRUE","YORK":"FALSE","brand":"FERRUM CITY","flavor":"Ferrum City Cereal 11","juiceID":94},{"FREDERICK":"TRUE","GETTYSBURG":"TRUE","LEMOYNE":"TRUE","YORK":"TRUE","brand":"FERRUM CITY","flavor":"Forged","juiceID":95},{"FREDERICK":"TRUE","GETTYSBURG":"FALSE","LEMOYNE":"TRUE","YORK":"FALSE","brand":"FERRUM CITY","flavor":"Fried Banana","juiceID":96},{"FREDERICK":"TRUE","GETTYSBURG":"TRUE","LEMOYNE":"TRUE","YORK":"TRUE","brand":"FERRUM CITY","flavor":"Lucked Up","juiceID":97},{"FREDERICK":"TRUE","GETTYSBURG":"TRUE","LEMOYNE":"TRUE","YORK":"TRUE","brand":"FERRUM CITY","flavor":"Mynt","juiceID":98},{"FREDERICK":"TRUE","GETTYSBURG":"FALSE","LEMOYNE":"TRUE","YORK":"TRUE","brand":"FERRUM CITY","flavor":"Poured","juiceID":99},{"FREDERICK":"TRUE","GETTYSBURG":"TRUE","LEMOYNE":"TRUE","YORK":"TRUE","brand":"FERRUM CITY","flavor":"Scary Berry","juiceID":100},{"FREDERICK":"TRUE","GETTYSBURG":"TRUE","LEMOYNE":"TRUE","YORK":"TRUE","brand":"FERRUM CITY","flavor":"Smelted","juiceID":101},{"FREDERICK":"TRUE","GETTYSBURG":"TRUE","LEMOYNE":"TRUE","YORK":"TRUE","brand":"FROZEN FRUIT MONSTER","flavor":"Banana Ice","juiceID":102},{"FREDERICK":"TRUE","GETTYSBURG":"TRUE","LEMOYNE":"TRUE","YORK":"TRUE","brand":"FROZEN FRUIT MONSTER","flavor":"Blueberry Raspberry Lemon Ice","juiceID":103},{"FREDERICK":"TRUE","GETTYSBURG":"TRUE","LEMOYNE":"TRUE","YORK":"TRUE","brand":"FROZEN FRUIT MONSTER","flavor":"Mango Peach Guava Ice","juiceID":104},{"FREDERICK":"TRUE","GETTYSBURG":"TRUE","LEMOYNE":"TRUE","YORK":"TRUE","brand":"FROZEN FRUIT MONSTER","flavor":"Mixed Berry Ice","juiceID":105},{"FREDERICK":"TRUE","GETTYSBURG":"FALSE","LEMOYNE":"TRUE","YORK":"TRUE","brand":"FROZEN FRUIT MONSTER","flavor":"Passionfruit Orange Guava Ice","juiceID":106},{"FREDERICK":"TRUE","GETTYSBURG":"TRUE","LEMOYNE":"TRUE","YORK":"TRUE","brand":"FRUIT MONSTER","flavor":"Blueberry Raspberry Lemon","juiceID":107},{"FREDERICK":"TRUE","GETTYSBURG":"TRUE","LEMOYNE":"TRUE","YORK":"TRUE","brand":"FRUIT MONSTER","flavor":"Mango Peach Guava","juiceID":108},{"FREDERICK":"TRUE","GETTYSBURG":"TRUE","LEMOYNE":"TRUE","YORK":"TRUE","brand":"FRUIT MONSTER","flavor":"Mixed Berry","juiceID":109},{"FREDERICK":"TRUE","GETTYSBURG":"TRUE","LEMOYNE":"TRUE","YORK":"TRUE","brand":"FRUIT MONSTER","flavor":"Passionfruit Orange Guava","juiceID":110},{"FREDERICK":"TRUE","GETTYSBURG":"TRUE","LEMOYNE":"TRUE","YORK":"TRUE","brand":"FRUIT MONSTER","flavor":"Strawberry Kiwi Pomegranate","juiceID":111},{"FREDERICK":"FALSE","GETTYSBURG":"FALSE","LEMOYNE":"TRUE","YORK":"FALSE","brand":"HALO","flavor":"Sub Zero","juiceID":112},{"FREDERICK":"FALSE","GETTYSBURG":"FALSE","LEMOYNE":"TRUE","YORK":"FALSE","brand":"HALO","flavor":"Tribeca","juiceID":113},{"FREDERICK":"FALSE","GETTYSBURG":"FALSE","LEMOYNE":"TRUE","YORK":"FALSE","brand":"I LOVE SALTS","flavor":"Classic Menthol","juiceID":114},{"FREDERICK":"TRUE","GETTYSBURG":"TRUE","LEMOYNE":"TRUE","YORK":"TRUE","brand":"I LOVE SALTS","flavor":"Spearmint Gum","juiceID":115},{"FREDERICK":"TRUE","GETTYSBURG":"TRUE","LEMOYNE":"TRUE","YORK":"TRUE","brand":"ICE MONSTER","flavor":"Mangerine Guava","juiceID":116},{"FREDERICK":"TRUE","GETTYSBURG":"TRUE","LEMOYNE":"TRUE","YORK":"TRUE","brand":"ICE MONSTER","flavor":"Melon Colada","juiceID":117},{"FREDERICK":"TRUE","GETTYSBURG":"TRUE","LEMOYNE":"TRUE","YORK":"TRUE","brand":"ICE MONSTER","flavor":"Strawmelon Apple","juiceID":118},{"FREDERICK":"TRUE","GETTYSBURG":"FALSE","LEMOYNE":"TRUE","YORK":"FALSE","brand":"INNEVAPE","flavor":"Heisenberg Menthol","juiceID":119},{"FREDERICK":"TRUE","GETTYSBURG":"TRUE","LEMOYNE":"TRUE","YORK":"TRUE","brand":"INNEVAPE","flavor":"The Berg","juiceID":120},{"FREDERICK":"TRUE","GETTYSBURG":"TRUE","LEMOYNE":"TRUE","YORK":"TRUE","brand":"INNEVAPE","flavor":"The Berg Menthol","juiceID":121},{"FREDERICK":"TRUE","GETTYSBURG":"TRUE","LEMOYNE":"TRUE","YORK":"TRUE","brand":"JAM MONSTER","flavor":"Blackberry","juiceID":122},{"FREDERICK":"TRUE","GETTYSBURG":"TRUE","LEMOYNE":"TRUE","YORK":"TRUE","brand":"JAM MONSTER","flavor":"Blueberry","juiceID":123},{"FREDERICK":"FALSE","GETTYSBURG":"FALSE","LEMOYNE":"TRUE","YORK":"FALSE","brand":"JAM MONSTER","flavor":"Lemon","juiceID":124},{"FREDERICK":"FALSE","GETTYSBURG":"FALSE","LEMOYNE":"TRUE","YORK":"TRUE","brand":"JAM MONSTER","flavor":"Mixed Berry","juiceID":125},{"FREDERICK":"FALSE","GETTYSBURG":"FALSE","LEMOYNE":"TRUE","YORK":"FALSE","brand":"JAM MONSTER","flavor":"PB Banana","juiceID":126},{"FREDERICK":"FALSE","GETTYSBURG":"TRUE","LEMOYNE":"TRUE","YORK":"FALSE","brand":"JAM MONSTER","flavor":"PB Jam Grape","juiceID":127},{"FREDERICK":"FALSE","GETTYSBURG":"FALSE","LEMOYNE":"TRUE","YORK":"FALSE","brand":"JAM MONSTER","flavor":"PB Jam Strawberry","juiceID":128},{"FREDERICK":"TRUE","GETTYSBURG":"TRUE","LEMOYNE":"TRUE","YORK":"FALSE","brand":"JAM MONSTER","flavor":"Raspberry","juiceID":129},{"FREDERICK":"TRUE","GETTYSBURG":"TRUE","LEMOYNE":"TRUE","YORK":"TRUE","brand":"JAM MONSTER","flavor":"Strawberry","juiceID":130},{"FREDERICK":"TRUE","GETTYSBURG":"TRUE","LEMOYNE":"TRUE","YORK":"TRUE","brand":"JUICE HEAD","flavor":"Blueberry Lemon","juiceID":131},{"FREDERICK":"TRUE","GETTYSBURG":"FALSE","LEMOYNE":"TRUE","YORK":"TRUE","brand":"JUICE HEAD","flavor":"Guava Peach","juiceID":132},{"FREDERICK":"TRUE","GETTYSBURG":"FALSE","LEMOYNE":"TRUE","YORK":"TRUE","brand":"JUICE HEAD","flavor":"Mango Strawberry","juiceID":133},{"FREDERICK":"TRUE","GETTYSBURG":"TRUE","LEMOYNE":"TRUE","YORK":"TRUE","brand":"JUICE HEAD","flavor":"Peach Pear","juiceID":134},{"FREDERICK":"TRUE","GETTYSBURG":"TRUE","LEMOYNE":"TRUE","YORK":"TRUE","brand":"JUICE HEAD","flavor":"Pineapple Grapefruit","juiceID":135},{"FREDERICK":"TRUE","GETTYSBURG":"TRUE","LEMOYNE":"TRUE","YORK":"TRUE","brand":"JUICE HEAD","flavor":"Strawberry Kiwi","juiceID":136},{"FREDERICK":"TRUE","GETTYSBURG":"TRUE","LEMOYNE":"TRUE","YORK":"TRUE","brand":"JUICE HEAD","flavor":"Watermelon Lime","juiceID":137},{"FREDERICK":"TRUE","GETTYSBURG":"TRUE","LEMOYNE":"TRUE","YORK":"TRUE","brand":"JUICE HEAD FREEZE","flavor":"Blueberry Lemon Freeze","juiceID":138},{"FREDERICK":"TRUE","GETTYSBURG":"FALSE","LEMOYNE":"TRUE","YORK":"TRUE","brand":"JUICE HEAD FREEZE","flavor":"Guava Peach Freeze","juiceID":139},{"FREDERICK":"TRUE","GETTYSBURG":"FALSE","LEMOYNE":"TRUE","YORK":"TRUE","brand":"JUICE HEAD FREEZE","flavor":"Mango Strawberry Freeze","juiceID":140},{"FREDERICK":"TRUE","GETTYSBURG":"TRUE","LEMOYNE":"TRUE","YORK":"TRUE","brand":"JUICE HEAD FREEZE","flavor":"Peach Pear Freeze","juiceID":141},{"FREDERICK":"TRUE","GETTYSBURG":"TRUE","LEMOYNE":"TRUE","YORK":"TRUE","brand":"JUICE HEAD FREEZE","flavor":"Pineapple Grapefruit Freeze","juiceID":142},{"FREDERICK":"TRUE","GETTYSBURG":"TRUE","LEMOYNE":"TRUE","YORK":"TRUE","brand":"JUICE HEAD FREEZE","flavor":"Strawberry Kiwi Freeze","juiceID":143},{"FREDERICK":"TRUE","GETTYSBURG":"TRUE","LEMOYNE":"TRUE","YORK":"TRUE","brand":"JUICE HEAD FREEZE","flavor":"Watermelon Lime Freeze","juiceID":144},{"FREDERICK":"TRUE","GETTYSBURG":"TRUE","LEMOYNE":"TRUE","YORK":"TRUE","brand":"JUICE ROLL UPZ","flavor":"Blue Raspberry","juiceID":145},{"FREDERICK":"TRUE","GETTYSBURG":"TRUE","LEMOYNE":"TRUE","YORK":"TRUE","brand":"JUICE ROLL UPZ","flavor":"Blue Raspberry Ice","juiceID":146},{"FREDERICK":"TRUE","GETTYSBURG":"TRUE","LEMOYNE":"TRUE","YORK":"TRUE","brand":"JUICE ROLL UPZ","flavor":"Grape","juiceID":147},{"FREDERICK":"TRUE","GETTYSBURG":"TRUE","LEMOYNE":"TRUE","YORK":"TRUE","brand":"JUICE ROLL UPZ","flavor":"Grape Ice","juiceID":148},{"FREDERICK":"TRUE","GETTYSBURG":"TRUE","LEMOYNE":"TRUE","YORK":"TRUE","brand":"JUICE ROLL UPZ","flavor":"Green Apple","juiceID":149},{"FREDERICK":"TRUE","GETTYSBURG":"TRUE","LEMOYNE":"TRUE","YORK":"TRUE","brand":"JUICE ROLL UPZ","flavor":"Green Apple Ice","juiceID":150},{"FREDERICK":"TRUE","GETTYSBURG":"TRUE","LEMOYNE":"TRUE","YORK":"TRUE","brand":"JUICE ROLL UPZ","flavor":"Red Razz","juiceID":151},{"FREDERICK":"TRUE","GETTYSBURG":"TRUE","LEMOYNE":"TRUE","YORK":"TRUE","brand":"JUICE ROLL UPZ","flavor":"Red Razz Ice","juiceID":152},{"FREDERICK":"TRUE","GETTYSBURG":"TRUE","LEMOYNE":"TRUE","YORK":"TRUE","brand":"JUICE ROLL UPZ","flavor":"Strawberry","juiceID":153},{"FREDERICK":"TRUE","GETTYSBURG":"TRUE","LEMOYNE":"TRUE","YORK":"TRUE","brand":"JUICE ROLL UPZ","flavor":"Strawberry Ice","juiceID":154},{"FREDERICK":"TRUE","GETTYSBURG":"TRUE","LEMOYNE":"TRUE","YORK":"FALSE","brand":"JUICE ROLL UPZ","flavor":"Watermelon Ice","juiceID":155},{"FREDERICK":"TRUE","GETTYSBURG":"TRUE","LEMOYNE":"TRUE","YORK":"TRUE","brand":"JUICE ROLL UPZ","flavor":"Watermelon Punch","juiceID":156},{"FREDERICK":"TRUE","GETTYSBURG":"TRUE","LEMOYNE":"TRUE","YORK":"TRUE","brand":"JUICE ROLL UPZ","flavor":"Watermelon Punch ICE","juiceID":157},{"FREDERICK":"TRUE","GETTYSBURG":"FALSE","LEMOYNE":"TRUE","YORK":"TRUE","brand":"JUICE ROLL UPZ","flavor":"Wild Berry","juiceID":158},{"FREDERICK":"TRUE","GETTYSBURG":"TRUE","LEMOYNE":"TRUE","YORK":"TRUE","brand":"JUICE ROLL UPZ","flavor":"Wild Berry Ice","juiceID":159},{"FREDERICK":"FALSE","GETTYSBURG":"FALSE","LEMOYNE":"TRUE","YORK":"FALSE","brand":"KEEP IT 100","flavor":"Maui Blast","juiceID":160},{"FREDERICK":"FALSE","GETTYSBURG":"FALSE","LEMOYNE":"TRUE","YORK":"FALSE","brand":"KEEP IT 100","flavor":"OG Blue","juiceID":161},{"FREDERICK":"FALSE","GETTYSBURG":"FALSE","LEMOYNE":"TRUE","YORK":"FALSE","brand":"KEEP IT 100","flavor":"OG Island Fusion","juiceID":162},{"FREDERICK":"FALSE","GETTYSBURG":"FALSE","LEMOYNE":"TRUE","YORK":"TRUE","brand":"KEEP IT 100","flavor":"OG Summer Blue","juiceID":163},{"FREDERICK":"FALSE","GETTYSBURG":"FALSE","LEMOYNE":"TRUE","YORK":"TRUE","brand":"KEEP IT 100","flavor":"OG Tropical Blue","juiceID":164},{"FREDERICK":"FALSE","GETTYSBURG":"FALSE","LEMOYNE":"TRUE","YORK":"FALSE","brand":"KEEP IT 100","flavor":"Shake","juiceID":165},{"FREDERICK":"TRUE","GETTYSBURG":"TRUE","LEMOYNE":"TRUE","YORK":"FALSE","brand":"KILLA FRUITS","flavor":"Blue Raspberry","juiceID":166},{"FREDERICK":"TRUE","GETTYSBURG":"TRUE","LEMOYNE":"TRUE","YORK":"FALSE","brand":"KILLA FRUITS","flavor":"Red Apple Peach","juiceID":167},{"FREDERICK":"TRUE","GETTYSBURG":"TRUE","LEMOYNE":"TRUE","YORK":"FALSE","brand":"KILLA FRUITS","flavor":"Strawberry Acai","juiceID":168},{"FREDERICK":"TRUE","GETTYSBURG":"TRUE","LEMOYNE":"TRUE","YORK":"FALSE","brand":"KILLA FRUITS","flavor":"Watermelon Strawberry","juiceID":169},{"FREDERICK":"FALSE","GETTYSBURG":"TRUE","LEMOYNE":"TRUE","YORK":"FALSE","brand":"MET4","flavor":"Golden Ticket","juiceID":170},{"FREDERICK":"FALSE","GETTYSBURG":"TRUE","LEMOYNE":"TRUE","YORK":"FALSE","brand":"MET4","flavor":"Pacific Sangha","juiceID":171},{"FREDERICK":"FALSE","GETTYSBURG":"TRUE","LEMOYNE":"TRUE","YORK":"FALSE","brand":"MICRO BREW","flavor":"Goat Herder","juiceID":172},{"FREDERICK":"TRUE","GETTYSBURG":"TRUE","LEMOYNE":"TRUE","YORK":"TRUE","brand":"MICRO BREW","flavor":"Grumpy Old Bastard","juiceID":173},{"FREDERICK":"TRUE","GETTYSBURG":"TRUE","LEMOYNE":"TRUE","YORK":"TRUE","brand":"MICRO BREW","flavor":"One Eyed Turtle","juiceID":174},{"FREDERICK":"FALSE","GETTYSBURG":"TRUE","LEMOYNE":"TRUE","YORK":"FALSE","brand":"MICRO BREW","flavor":"Secret Handshake","juiceID":175},{"FREDERICK":"FALSE","GETTYSBURG":"TRUE","LEMOYNE":"TRUE","YORK":"TRUE","brand":"MIGHTY VAPORS","flavor":"Frozen Hulk Tears","juiceID":176},{"FREDERICK":"TRUE","GETTYSBURG":"FALSE","LEMOYNE":"TRUE","YORK":"TRUE","brand":"MIGHTY VAPORS","flavor":"Hulk Tears","juiceID":177},{"FREDERICK":"TRUE","GETTYSBURG":"FALSE","LEMOYNE":"TRUE","YORK":"FALSE","brand":"MR. FREEZE","flavor":"Apple Frost","juiceID":178},{"FREDERICK":"FALSE","GETTYSBURG":"FALSE","LEMOYNE":"TRUE","YORK":"FALSE","brand":"MR. FREEZE","flavor":"Berry Frost","juiceID":179},{"FREDERICK":"TRUE","GETTYSBURG":"FALSE","LEMOYNE":"TRUE","YORK":"FALSE","brand":"MR. FREEZE","flavor":"Strawberry Watermelon Frost","juiceID":180},{"FREDERICK":"TRUE","GETTYSBURG":"FALSE","LEMOYNE":"TRUE","YORK":"TRUE","brand":"MR. FREEZE","flavor":"Tobacco Menthol","juiceID":181},{"FREDERICK":"FALSE","GETTYSBURG":"TRUE","LEMOYNE":"TRUE","YORK":"TRUE","brand":"NAKED100","flavor":"Berry","juiceID":182},{"FREDERICK":"TRUE","GETTYSBURG":"FALSE","LEMOYNE":"TRUE","YORK":"TRUE","brand":"NAKED100","flavor":"Crisp Menthol","juiceID":183},{"FREDERICK":"TRUE","GETTYSBURG":"TRUE","LEMOYNE":"TRUE","YORK":"TRUE","brand":"NAKED100","flavor":"Hawaiian Pog","juiceID":184},{"FREDERICK":"TRUE","GETTYSBURG":"TRUE","LEMOYNE":"TRUE","YORK":"TRUE","brand":"NAKED100","flavor":"Lava Flow","juiceID":185},{"FREDERICK":"FALSE","GETTYSBURG":"FALSE","LEMOYNE":"TRUE","YORK":"TRUE","brand":"NAKED100","flavor":"Melon","juiceID":186},{"FREDERICK":"TRUE","GETTYSBURG":"TRUE","LEMOYNE":"TRUE","YORK":"FALSE","brand":"NAKED100","flavor":"Really Berry","juiceID":187},{"FREDERICK":"FALSE","GETTYSBURG":"TRUE","LEMOYNE":"TRUE","YORK":"TRUE","brand":"NAKED100","flavor":"Strawberry Pom","juiceID":188},{"FREDERICK":"FALSE","GETTYSBURG":"FALSE","LEMOYNE":"TRUE","YORK":"FALSE","brand":"NITRO'S COLD BREW COFFEE","flavor":"Almond Cappuccino","juiceID":189},{"FREDERICK":"FALSE","GETTYSBURG":"FALSE","LEMOYNE":"TRUE","YORK":"FALSE","brand":"NITRO'S COLD BREW COFFEE","flavor":"Macchiato","juiceID":190},{"FREDERICK":"FALSE","GETTYSBURG":"FALSE","LEMOYNE":"TRUE","YORK":"FALSE","brand":"NITRO'S COLD BREW COFFEE","flavor":"Vanilla Bean","juiceID":191},{"FREDERICK":"TRUE","GETTYSBURG":"TRUE","LEMOYNE":"TRUE","YORK":"TRUE","brand":"NOMS","flavor":"Blueberry Papaya Strawberry","juiceID":192},{"FREDERICK":"TRUE","GETTYSBURG":"FALSE","LEMOYNE":"TRUE","YORK":"TRUE","brand":"NOMS","flavor":"Blunomenon","juiceID":193},{"FREDERICK":"TRUE","GETTYSBURG":"FALSE","LEMOYNE":"TRUE","YORK":"TRUE","brand":"NOMS","flavor":"Blunomenon Ice","juiceID":194},{"FREDERICK":"TRUE","GETTYSBURG":"TRUE","LEMOYNE":"TRUE","YORK":"TRUE","brand":"NOMS","flavor":"Cactus Jackfruit Mandarin","juiceID":195},{"FREDERICK":"TRUE","GETTYSBURG":"TRUE","LEMOYNE":"TRUE","YORK":"TRUE","brand":"NOMS","flavor":"Cherry Lime Ginger","juiceID":196},{"FREDERICK":"TRUE","GETTYSBURG":"FALSE","LEMOYNE":"TRUE","YORK":"TRUE","brand":"NOMS","flavor":"Kiwi Passion Fruit Nectarine","juiceID":197},{"FREDERICK":"TRUE","GETTYSBURG":"FALSE","LEMOYNE":"TRUE","YORK":"TRUE","brand":"NOMS","flavor":"Lemonomenon","juiceID":198},{"FREDERICK":"TRUE","GETTYSBURG":"FALSE","LEMOYNE":"TRUE","YORK":"TRUE","brand":"NOMS","flavor":"Spearnomenon","juiceID":199},{"FREDERICK":"TRUE","GETTYSBURG":"TRUE","LEMOYNE":"TRUE","YORK":"TRUE","brand":"NOMS","flavor":"White Peach Raspberry","juiceID":200},{"FREDERICK":"TRUE","GETTYSBURG":"FALSE","LEMOYNE":"TRUE","YORK":"TRUE","brand":"ONE HIT WONDER","flavor":"Army Man","juiceID":201},{"FREDERICK":"TRUE","GETTYSBURG":"TRUE","LEMOYNE":"TRUE","YORK":"TRUE","brand":"ONE HIT WONDER","flavor":"Island Man","juiceID":202},{"FREDERICK":"TRUE","GETTYSBURG":"TRUE","LEMOYNE":"TRUE","YORK":"TRUE","brand":"ONE HIT WONDER","flavor":"Island Man Ice","juiceID":203},{"FREDERICK":"TRUE","GETTYSBURG":"FALSE","LEMOYNE":"TRUE","YORK":"TRUE","brand":"ONE HIT WONDER","flavor":"Mini Muffin Man","juiceID":204},{"FREDERICK":"TRUE","GETTYSBURG":"FALSE","LEMOYNE":"TRUE","YORK":"TRUE","brand":"ONE HIT WONDER","flavor":"Muffin Man","juiceID":205},{"FREDERICK":"TRUE","GETTYSBURG":"FALSE","LEMOYNE":"TRUE","YORK":"TRUE","brand":"ONE HIT WONDER","flavor":"The Man","juiceID":206},{"FREDERICK":"FALSE","GETTYSBURG":"FALSE","LEMOYNE":"TRUE","YORK":"TRUE","brand":"ONE UP","flavor":"Orgasm","juiceID":207},{"FREDERICK":"FALSE","GETTYSBURG":"FALSE","LEMOYNE":"TRUE","YORK":"TRUE","brand":"ONE UP","flavor":"Orgasm Ice","juiceID":208},{"FREDERICK":"FALSE","GETTYSBURG":"FALSE","LEMOYNE":"TRUE","YORK":"FALSE","brand":"ONE UP","flavor":"Strawberry Gummy","juiceID":209},{"FREDERICK":"FALSE","GETTYSBURG":"FALSE","LEMOYNE":"TRUE","YORK":"FALSE","brand":"ONE UP","flavor":"Watermelon Gummy","juiceID":210},{"FREDERICK":"TRUE","GETTYSBURG":"FALSE","LEMOYNE":"TRUE","YORK":"TRUE","brand":"PACHA MAMA","flavor":"Apple Tobacco","juiceID":211},{"FREDERICK":"TRUE","GETTYSBURG":"TRUE","LEMOYNE":"TRUE","YORK":"TRUE","brand":"PACHA MAMA","flavor":"Blood Orange Banana Gooseberry","juiceID":212},{"FREDERICK":"TRUE","GETTYSBURG":"FALSE","LEMOYNE":"TRUE","YORK":"TRUE","brand":"PACHA MAMA","flavor":"Fuji","juiceID":213},{"FREDERICK":"TRUE","GETTYSBURG":"TRUE","LEMOYNE":"TRUE","YORK":"FALSE","brand":"PACHA MAMA","flavor":"Fuji Apple Strawberry Nectarine","juiceID":214},{"FREDERICK":"TRUE","GETTYSBURG":"FALSE","LEMOYNE":"TRUE","YORK":"FALSE","brand":"PACHA MAMA","flavor":"Honeydew Berry Kiwi","juiceID":215},{"FREDERICK":"TRUE","GETTYSBURG":"FALSE","LEMOYNE":"TRUE","YORK":"TRUE","brand":"PACHA MAMA","flavor":"Honeydew Melon","juiceID":216},{"FREDERICK":"TRUE","GETTYSBURG":"FALSE","LEMOYNE":"TRUE","YORK":"TRUE","brand":"PACHA MAMA","flavor":"Icey Mango","juiceID":217},{"FREDERICK":"TRUE","GETTYSBURG":"FALSE","LEMOYNE":"TRUE","YORK":"TRUE","brand":"PACHA MAMA","flavor":"Peach Papaya Coconut","juiceID":218},{"FREDERICK":"TRUE","GETTYSBURG":"FALSE","LEMOYNE":"TRUE","YORK":"TRUE","brand":"PACHA MAMA","flavor":"Sorbet","juiceID":219},{"FREDERICK":"TRUE","GETTYSBURG":"FALSE","LEMOYNE":"TRUE","YORK":"TRUE","brand":"PACHA MAMA","flavor":"Starfruit Grape","juiceID":220},{"FREDERICK":"TRUE","GETTYSBURG":"FALSE","LEMOYNE":"TRUE","YORK":"TRUE","brand":"PACHA MAMA","flavor":"Strawberry Watermelon","juiceID":221},{"FREDERICK":"TRUE","GETTYSBURG":"FALSE","LEMOYNE":"TRUE","YORK":"FALSE","brand":"PINUP","flavor":"Betty","juiceID":222},{"FREDERICK":"TRUE","GETTYSBURG":"FALSE","LEMOYNE":"TRUE","YORK":"FALSE","brand":"PINUP","flavor":"Betty Chill","juiceID":223},{"FREDERICK":"TRUE","GETTYSBURG":"FALSE","LEMOYNE":"TRUE","YORK":"FALSE","brand":"PINUP","flavor":"Christie","juiceID":224},{"FREDERICK":"TRUE","GETTYSBURG":"TRUE","LEMOYNE":"TRUE","YORK":"TRUE","brand":"PROHIBITION","flavor":"18th Amendment","juiceID":225},{"FREDERICK":"TRUE","GETTYSBURG":"TRUE","LEMOYNE":"TRUE","YORK":"TRUE","brand":"PROHIBITION","flavor":"Riding Shotgun","juiceID":226},{"FREDERICK":"FALSE","GETTYSBURG":"TRUE","LEMOYNE":"TRUE","YORK":"TRUE","brand":"PROHIBITION","flavor":"Sin Tax","juiceID":227},{"FREDERICK":"TRUE","GETTYSBURG":"FALSE","LEMOYNE":"TRUE","YORK":"TRUE","brand":"PROHIBITION","flavor":"Speakeasy","juiceID":228},{"FREDERICK":"FALSE","GETTYSBURG":"FALSE","LEMOYNE":"TRUE","YORK":"FALSE","brand":"PROPHET PREMIUM","flavor":"Chew","juiceID":229},{"FREDERICK":"TRUE","GETTYSBURG":"TRUE","LEMOYNE":"TRUE","YORK":"FALSE","brand":"REDS","flavor":"Apple ICE","juiceID":230},{"FREDERICK":"TRUE","GETTYSBURG":"TRUE","LEMOYNE":"TRUE","YORK":"FALSE","brand":"REDS","flavor":"Apple","juiceID":231},{"FREDERICK":"TRUE","GETTYSBURG":"FALSE","LEMOYNE":"TRUE","YORK":"FALSE","brand":"REDS","flavor":"Berries","juiceID":232},{"FREDERICK":"FALSE","GETTYSBURG":"FALSE","LEMOYNE":"TRUE","YORK":"FALSE","brand":"REDS","flavor":"Berries Ice","juiceID":233},{"FREDERICK":"TRUE","GETTYSBURG":"TRUE","LEMOYNE":"TRUE","YORK":"FALSE","brand":"REDS","flavor":"Grape","juiceID":234},{"FREDERICK":"TRUE","GETTYSBURG":"TRUE","LEMOYNE":"TRUE","YORK":"FALSE","brand":"REDS","flavor":"Grape ICE","juiceID":235},{"FREDERICK":"FALSE","GETTYSBURG":"FALSE","LEMOYNE":"TRUE","YORK":"FALSE","brand":"REDS","flavor":"Strawberry","juiceID":236},{"FREDERICK":"FALSE","GETTYSBURG":"TRUE","LEMOYNE":"TRUE","YORK":"FALSE","brand":"REDS","flavor":"Strawberry Ice","juiceID":237},{"FREDERICK":"TRUE","GETTYSBURG":"TRUE","LEMOYNE":"TRUE","YORK":"FALSE","brand":"SAD BOY","flavor":"Blueberry Nola bar","juiceID":238},{"FREDERICK":"TRUE","GETTYSBURG":"FALSE","LEMOYNE":"TRUE","YORK":"TRUE","brand":"SAD BOY","flavor":"Blueberry Jam Cookie","juiceID":239},{"FREDERICK":"TRUE","GETTYSBURG":"TRUE","LEMOYNE":"TRUE","YORK":"TRUE","brand":"SAD BOY","flavor":"Custard Cookie","juiceID":240},{"FREDERICK":"TRUE","GETTYSBURG":"TRUE","LEMOYNE":"TRUE","YORK":"TRUE","brand":"SAD BOY","flavor":"Happy End","juiceID":241},{"FREDERICK":"FALSE","GETTYSBURG":"TRUE","LEMOYNE":"TRUE","YORK":"TRUE","brand":"SAD BOY","flavor":"Key Lime Cookie","juiceID":242},{"FREDERICK":"TRUE","GETTYSBURG":"FALSE","LEMOYNE":"TRUE","YORK":"FALSE","brand":"SAD BOY","flavor":"Orphan's Blood","juiceID":243},{"FREDERICK":"TRUE","GETTYSBURG":"FALSE","LEMOYNE":"TRUE","YORK":"FALSE","brand":"SAD BOY","flavor":"Pumpkin Cookie","juiceID":244},{"FREDERICK":"TRUE","GETTYSBURG":"TRUE","LEMOYNE":"TRUE","YORK":"TRUE","brand":"SAD BOY","flavor":"Shamrock Cookie","juiceID":245},{"FREDERICK":"TRUE","GETTYSBURG":"TRUE","LEMOYNE":"TRUE","YORK":"FALSE","brand":"SAD BOY","flavor":"Strawberry Nola bar","juiceID":246},{"FREDERICK":"TRUE","GETTYSBURG":"TRUE","LEMOYNE":"TRUE","YORK":"FALSE","brand":"SAD BOY","flavor":"Unicorn Tears","juiceID":247},{"FREDERICK":"TRUE","GETTYSBURG":"FALSE","LEMOYNE":"TRUE","YORK":"FALSE","brand":"SALT BAE","flavor":"Banana Ice","juiceID":248},{"FREDERICK":"TRUE","GETTYSBURG":"TRUE","LEMOYNE":"TRUE","YORK":"TRUE","brand":"SALT BAE","flavor":"Blue Razz Lemonade","juiceID":249},{"FREDERICK":"TRUE","GETTYSBURG":"TRUE","LEMOYNE":"TRUE","YORK":"TRUE","brand":"SALT BAE","flavor":"Blue Razz Lemonade Ice","juiceID":250},{"FREDERICK":"TRUE","GETTYSBURG":"FALSE","LEMOYNE":"TRUE","YORK":"FALSE","brand":"SALT BAE","flavor":"Caramel Tobacco","juiceID":251},{"FREDERICK":"TRUE","GETTYSBURG":"TRUE","LEMOYNE":"TRUE","YORK":"TRUE","brand":"SALT BAE","flavor":"Fresh Pineapple","juiceID":252},{"FREDERICK":"TRUE","GETTYSBURG":"TRUE","LEMOYNE":"TRUE","YORK":"FALSE","brand":"SALT BAE","flavor":"Fruit Punch","juiceID":253},{"FREDERICK":"TRUE","GETTYSBURG":"TRUE","LEMOYNE":"TRUE","YORK":"FALSE","brand":"SALT BAE","flavor":"Georgia Peach","juiceID":254},{"FREDERICK":"TRUE","GETTYSBURG":"FALSE","LEMOYNE":"TRUE","YORK":"FALSE","brand":"SALT BAE","flavor":"Grape Kiwi","juiceID":255},{"FREDERICK":"FALSE","GETTYSBURG":"FALSE","LEMOYNE":"TRUE","YORK":"TRUE","brand":"SALT BAE","flavor":"Green Apple","juiceID":256},{"FREDERICK":"TRUE","GETTYSBURG":"TRUE","LEMOYNE":"TRUE","YORK":"FALSE","brand":"SALT BAE","flavor":"HoneyDew Ice","juiceID":257},{"FREDERICK":"TRUE","GETTYSBURG":"TRUE","LEMOYNE":"TRUE","YORK":"TRUE","brand":"SALT BAE","flavor":"Juicy Watermelon","juiceID":258},{"FREDERICK":"TRUE","GETTYSBURG":"TRUE","LEMOYNE":"TRUE","YORK":"TRUE","brand":"SALT BAE","flavor":"Juicy Watermelon Ice","juiceID":259},{"FREDERICK":"TRUE","GETTYSBURG":"TRUE","LEMOYNE":"TRUE","YORK":"TRUE","brand":"SALT BAE","flavor":"Red Mango","juiceID":260},{"FREDERICK":"TRUE","GETTYSBURG":"TRUE","LEMOYNE":"TRUE","YORK":"TRUE","brand":"SALT BAE","flavor":"Red Mango Ice","juiceID":261},{"FREDERICK":"TRUE","GETTYSBURG":"FALSE","LEMOYNE":"TRUE","YORK":"FALSE","brand":"SALT BAE","flavor":"Strawberry Acai","juiceID":262},{"FREDERICK":"FALSE","GETTYSBURG":"TRUE","LEMOYNE":"TRUE","YORK":"TRUE","brand":"SALT BAE","flavor":"Strawberry Kiwi","juiceID":263},{"FREDERICK":"FALSE","GETTYSBURG":"FALSE","LEMOYNE":"TRUE","YORK":"FALSE","brand":"SALT BAE","flavor":"Winter Green","juiceID":264},{"FREDERICK":"FALSE","GETTYSBURG":"FALSE","LEMOYNE":"TRUE","YORK":"FALSE","brand":"SOLACE","flavor":"Banana Dragonberry","juiceID":265},{"FREDERICK":"FALSE","GETTYSBURG":"FALSE","LEMOYNE":"TRUE","YORK":"FALSE","brand":"SOLACE","flavor":"Berry Bash","juiceID":266},{"FREDERICK":"FALSE","GETTYSBURG":"FALSE","LEMOYNE":"TRUE","YORK":"FALSE","brand":"SOLACE","flavor":"Blue Raspberry Lemonade Ice","juiceID":267},{"FREDERICK":"FALSE","GETTYSBURG":"FALSE","LEMOYNE":"TRUE","YORK":"FALSE","brand":"SOLACE","flavor":"Blue's Mango","juiceID":268},{"FREDERICK":"FALSE","GETTYSBURG":"FALSE","LEMOYNE":"TRUE","YORK":"FALSE","brand":"SOLACE","flavor":"Cool Tobacco","juiceID":269},{"FREDERICK":"FALSE","GETTYSBURG":"FALSE","LEMOYNE":"TRUE","YORK":"FALSE","brand":"SOLACE","flavor":"Juiced Apple","juiceID":270},{"FREDERICK":"FALSE","GETTYSBURG":"FALSE","LEMOYNE":"TRUE","YORK":"FALSE","brand":"SOLACE","flavor":"Lemon Lime Fusion","juiceID":271},{"FREDERICK":"TRUE","GETTYSBURG":"TRUE","LEMOYNE":"TRUE","YORK":"TRUE","brand":"SOLACE","flavor":"Mint","juiceID":272},{"FREDERICK":"FALSE","GETTYSBURG":"FALSE","LEMOYNE":"TRUE","YORK":"FALSE","brand":"SOLACE","flavor":"Pineapple","juiceID":273},{"FREDERICK":"TRUE","GETTYSBURG":"TRUE","LEMOYNE":"TRUE","YORK":"FALSE","brand":"SOLACE","flavor":"Sea Salt Blueberry","juiceID":274},{"FREDERICK":"TRUE","GETTYSBURG":"FALSE","LEMOYNE":"TRUE","YORK":"FALSE","brand":"SOLACE","flavor":"Strawberry","juiceID":275},{"FREDERICK":"FALSE","GETTYSBURG":"FALSE","LEMOYNE":"TRUE","YORK":"FALSE","brand":"SOLACE","flavor":"Strawberry Kiwi Ice","juiceID":276},{"FREDERICK":"FALSE","GETTYSBURG":"FALSE","LEMOYNE":"TRUE","YORK":"FALSE","brand":"SOLACE","flavor":"Tropical Stawberry","juiceID":277},{"FREDERICK":"TRUE","GETTYSBURG":"TRUE","LEMOYNE":"TRUE","YORK":"TRUE","brand":"THE FINEST","flavor":"Apple Peach Sour","juiceID":278},{"FREDERICK":"TRUE","GETTYSBURG":"FALSE","LEMOYNE":"TRUE","YORK":"TRUE","brand":"THE FINEST","flavor":"Apple Pearadise","juiceID":279},{"FREDERICK":"TRUE","GETTYSBURG":"FALSE","LEMOYNE":"TRUE","YORK":"TRUE","brand":"THE FINEST","flavor":"Apple Pearadise Ice","juiceID":280},{"FREDERICK":"TRUE","GETTYSBURG":"FALSE","LEMOYNE":"TRUE","YORK":"TRUE","brand":"THE FINEST","flavor":"Berry Blast","juiceID":281},{"FREDERICK":"TRUE","GETTYSBURG":"FALSE","LEMOYNE":"TRUE","YORK":"TRUE","brand":"THE FINEST","flavor":"Berry Blast Ice","juiceID":282},{"FREDERICK":"TRUE","GETTYSBURG":"TRUE","LEMOYNE":"TRUE","YORK":"TRUE","brand":"THE FINEST","flavor":"Blueberrie Lemon Swirl","juiceID":283},{"FREDERICK":"TRUE","GETTYSBURG":"TRUE","LEMOYNE":"TRUE","YORK":"TRUE","brand":"THE FINEST","flavor":"Cool Mint","juiceID":284},{"FREDERICK":"TRUE","GETTYSBURG":"FALSE","LEMOYNE":"TRUE","YORK":"TRUE","brand":"THE FINEST","flavor":"Cotton Clouds","juiceID":285},{"FREDERICK":"FALSE","GETTYSBURG":"FALSE","LEMOYNE":"TRUE","YORK":"FALSE","brand":"THE FINEST","flavor":"Honey Banana","juiceID":286},{"FREDERICK":"TRUE","GETTYSBURG":"FALSE","LEMOYNE":"TRUE","YORK":"TRUE","brand":"THE FINEST","flavor":"Mango Berry","juiceID":287},{"FREDERICK":"TRUE","GETTYSBURG":"FALSE","LEMOYNE":"TRUE","YORK":"TRUE","brand":"THE FINEST","flavor":"Mango Berry Ice","juiceID":288},{"FREDERICK":"TRUE","GETTYSBURG":"TRUE","LEMOYNE":"TRUE","YORK":"TRUE","brand":"THE FINEST","flavor":"Straw Melon Sour","juiceID":289},{"FREDERICK":"TRUE","GETTYSBURG":"TRUE","LEMOYNE":"TRUE","YORK":"TRUE","brand":"THE FINEST","flavor":"Strawberry Chew","juiceID":290},{"FREDERICK":"TRUE","GETTYSBURG":"FALSE","LEMOYNE":"TRUE","YORK":"FALSE","brand":"THE FINEST","flavor":"Tiramisu Custard","juiceID":291},{"FREDERICK":"TRUE","GETTYSBURG":"TRUE","LEMOYNE":"TRUE","YORK":"TRUE","brand":"THE ONE","flavor":"Apple Cinnamon","juiceID":292},{"FREDERICK":"TRUE","GETTYSBURG":"TRUE","LEMOYNE":"TRUE","YORK":"TRUE","brand":"THE ONE","flavor":"Blueberry","juiceID":293},{"FREDERICK":"TRUE","GETTYSBURG":"TRUE","LEMOYNE":"TRUE","YORK":"FALSE","brand":"THE ONE","flavor":"Marshmallow Milk","juiceID":294},{"FREDERICK":"TRUE","GETTYSBURG":"TRUE","LEMOYNE":"TRUE","YORK":"TRUE","brand":"THE ONE","flavor":"Strawberry","juiceID":295},{"FREDERICK":"TRUE","GETTYSBURG":"FALSE","LEMOYNE":"TRUE","YORK":"TRUE","brand":"TRANSISTOR","flavor":"Basic B","juiceID":296},{"FREDERICK":"TRUE","GETTYSBURG":"TRUE","LEMOYNE":"TRUE","YORK":"TRUE","brand":"TRANSISTOR","flavor":"Bluetiful Disaster","juiceID":297},{"FREDERICK":"TRUE","GETTYSBURG":"TRUE","LEMOYNE":"TRUE","YORK":"TRUE","brand":"TRANSISTOR","flavor":"Carango","juiceID":298},{"FREDERICK":"TRUE","GETTYSBURG":"TRUE","LEMOYNE":"TRUE","YORK":"TRUE","brand":"TRANSISTOR","flavor":"Lem'n Berry","juiceID":299},{"FREDERICK":"FALSE","GETTYSBURG":"FALSE","LEMOYNE":"TRUE","YORK":"TRUE","brand":"TRANSISTOR","flavor":"Nazzo","juiceID":300},{"FREDERICK":"TRUE","GETTYSBURG":"TRUE","LEMOYNE":"TRUE","YORK":"TRUE","brand":"TRANSISTOR","flavor":"NectoChill","juiceID":301},{"FREDERICK":"FALSE","GETTYSBURG":"FALSE","LEMOYNE":"TRUE","YORK":"TRUE","brand":"TRANSISTOR","flavor":"NectoSphere","juiceID":302},{"FREDERICK":"TRUE","GETTYSBURG":"TRUE","LEMOYNE":"TRUE","YORK":"TRUE","brand":"TRANSISTOR","flavor":"Pango","juiceID":303},{"FREDERICK":"TRUE","GETTYSBURG":"TRUE","LEMOYNE":"TRUE","YORK":"TRUE","brand":"TRANSISTOR","flavor":"Phoenix","juiceID":304},{"FREDERICK":"TRUE","GETTYSBURG":"TRUE","LEMOYNE":"TRUE","YORK":"TRUE","brand":"TRANSISTOR","flavor":"Tango Melon","juiceID":305},{"FREDERICK":"FALSE","GETTYSBURG":"TRUE","LEMOYNE":"TRUE","YORK":"TRUE","brand":"TWIST","flavor":"Banana Amber","juiceID":306},{"FREDERICK":"FALSE","GETTYSBURG":"FALSE","LEMOYNE":"TRUE","YORK":"TRUE","brand":"TWIST","flavor":"Berry Amber","juiceID":307},{"FREDERICK":"TRUE","GETTYSBURG":"TRUE","LEMOYNE":"TRUE","YORK":"TRUE","brand":"TWIST","flavor":"Chilled Melon Remix","juiceID":308},{"FREDERICK":"FALSE","GETTYSBURG":"FALSE","LEMOYNE":"TRUE","YORK":"FALSE","brand":"TWIST","flavor":"Cocktail Blend","juiceID":309},{"FREDERICK":"FALSE","GETTYSBURG":"FALSE","LEMOYNE":"TRUE","YORK":"TRUE","brand":"TWIST","flavor":"Crimson No. 1","juiceID":310},{"FREDERICK":"FALSE","GETTYSBURG":"FALSE","LEMOYNE":"TRUE","YORK":"TRUE","brand":"TWIST","flavor":"Frosted Amber","juiceID":311},{"FREDERICK":"FALSE","GETTYSBURG":"FALSE","LEMOYNE":"TRUE","YORK":"TRUE","brand":"TWIST","flavor":"Green No. 1","juiceID":312},{"FREDERICK":"FALSE","GETTYSBURG":"FALSE","LEMOYNE":"TRUE","YORK":"TRUE","brand":"TWIST","flavor":"Mint No. 1","juiceID":313},{"FREDERICK":"FALSE","GETTYSBURG":"FALSE","LEMOYNE":"TRUE","YORK":"TRUE","brand":"TWIST","flavor":"Pink No.0","juiceID":314},{"FREDERICK":"FALSE","GETTYSBURG":"FALSE","LEMOYNE":"TRUE","YORK":"TRUE","brand":"TWIST","flavor":"Pink No. 1","juiceID":315},{"FREDERICK":"FALSE","GETTYSBURG":"FALSE","LEMOYNE":"TRUE","YORK":"TRUE","brand":"TWIST","flavor":"Purple Grape","juiceID":316},{"FREDERICK":"TRUE","GETTYSBURG":"FALSE","LEMOYNE":"TRUE","YORK":"TRUE","brand":"TWIST","flavor":"Purple No. 1","juiceID":317},{"FREDERICK":"FALSE","GETTYSBURG":"FALSE","LEMOYNE":"TRUE","YORK":"TRUE","brand":"TWIST","flavor":"Rainbow No. 1","juiceID":318},{"FREDERICK":"FALSE","GETTYSBURG":"FALSE","LEMOYNE":"TRUE","YORK":"TRUE","brand":"TWIST","flavor":"Red No. 1","juiceID":319},{"FREDERICK":"FALSE","GETTYSBURG":"FALSE","LEMOYNE":"TRUE","YORK":"TRUE","brand":"TWIST","flavor":"Sour Red","juiceID":320},{"FREDERICK":"FALSE","GETTYSBURG":"FALSE","LEMOYNE":"TRUE","YORK":"FALSE","brand":"TWIST","flavor":"White No. 1","juiceID":321},{"FREDERICK":"FALSE","GETTYSBURG":"FALSE","LEMOYNE":"TRUE","YORK":"TRUE","brand":"TWIST","flavor":"Wild Red","juiceID":322},{"FREDERICK":"FALSE","GETTYSBURG":"FALSE","LEMOYNE":"TRUE","YORK":"TRUE","brand":"TWIST","flavor":"Yellow Peach","juiceID":323},{"FREDERICK":"FALSE","GETTYSBURG":"FALSE","LEMOYNE":"TRUE","YORK":"TRUE","brand":"TWISTED TONGUE","flavor":"Cinnamon Swirl","juiceID":324},{"FREDERICK":"FALSE","GETTYSBURG":"FALSE","LEMOYNE":"TRUE","YORK":"TRUE","brand":"TWISTED TONGUE","flavor":"French Vanilla","juiceID":325},{"FREDERICK":"FALSE","GETTYSBURG":"FALSE","LEMOYNE":"TRUE","YORK":"TRUE","brand":"TWISTED TONGUE","flavor":"Fruit Cereal Milk","juiceID":326},{"FREDERICK":"FALSE","GETTYSBURG":"FALSE","LEMOYNE":"TRUE","YORK":"TRUE","brand":"TWISTED TONGUE","flavor":"Sugar Nana","juiceID":327},{"FREDERICK":"FALSE","GETTYSBURG":"FALSE","LEMOYNE":"TRUE","YORK":"TRUE","brand":"TWISTED TONGUE","flavor":"The Fix","juiceID":328},{"FREDERICK":"FALSE","GETTYSBURG":"FALSE","LEMOYNE":"TRUE","YORK":"TRUE","brand":"TWISTED TONGUE","flavor":"Wild Blue","juiceID":329},{"FREDERICK":"TRUE","GETTYSBURG":"TRUE","LEMOYNE":"TRUE","YORK":"FALSE","brand":"VAPETASIA","flavor":"Killer Kustard","juiceID":330},{"FREDERICK":"FALSE","GETTYSBURG":"FALSE","LEMOYNE":"TRUE","YORK":"FALSE","brand":"VGOD","flavor":"Cubano","juiceID":331},{"FREDERICK":"TRUE","GETTYSBURG":"FALSE","LEMOYNE":"FALSE","YORK":"FALSE","brand":"AIR FACTORY","flavor":"Blue Razz","juiceID":332},{"FREDERICK":"TRUE","GETTYSBURG":"FALSE","LEMOYNE":"FALSE","YORK":"FALSE","brand":"AIR FACTORY","flavor":"Mystery","juiceID":334},{"FREDERICK":"TRUE","GETTYSBURG":"FALSE","LEMOYNE":"FALSE","YORK":"FALSE","brand":"ALT ZERO","flavor":"Excision: Paradox","juiceID":335},{"FREDERICK":"TRUE","GETTYSBURG":"FALSE","LEMOYNE":"FALSE","YORK":"FALSE","brand":"ALT ZERO","flavor":"Paradox","juiceID":336},{"FREDERICK":"TRUE","GETTYSBURG":"FALSE","LEMOYNE":"FALSE","YORK":"FALSE","brand":"ALT ZERO","flavor":"Paradox on the Rocks","juiceID":337},{"FREDERICK":"TRUE","GETTYSBURG":"FALSE","LEMOYNE":"FALSE","YORK":"FALSE","brand":"ALT ZERO","flavor":"Robokitty","juiceID":338},{"FREDERICK":"TRUE","GETTYSBURG":"FALSE","LEMOYNE":"FALSE","YORK":"FALSE","brand":"ALT ZERO","flavor":"Virus","juiceID":339},{"FREDERICK":"TRUE","GETTYSBURG":"FALSE","LEMOYNE":"FALSE","YORK":"FALSE","brand":"BEARD VAPE CO","flavor":"No. 32","juiceID":343},{"FREDERICK":"TRUE","GETTYSBURG":"FALSE","LEMOYNE":"FALSE","YORK":"FALSE","brand":"BEARD VAPE CO","flavor":"No. 5","juiceID":344},{"FREDERICK":"TRUE","GETTYSBURG":"TRUE","LEMOYNE":"FALSE","YORK":"FALSE","brand":"BIG BOTTLE COMPANY","flavor":"Patches","juiceID":350},{"FREDERICK":"TRUE","GETTYSBURG":"TRUE","LEMOYNE":"FALSE","YORK":"FALSE","brand":"BIG F'N DEAL","flavor":"Berry Burst","juiceID":353},{"FREDERICK":"TRUE","GETTYSBURG":"TRUE","LEMOYNE":"FALSE","YORK":"FALSE","brand":"BIG F'N DEAL","flavor":"Citrus Burst","juiceID":355},{"FREDERICK":"TRUE","GETTYSBURG":"TRUE","LEMOYNE":"FALSE","YORK":"FALSE","brand":"BIG F'N DEAL","flavor":"Happy Melon","juiceID":356},{"FREDERICK":"TRUE","GETTYSBURG":"TRUE","LEMOYNE":"FALSE","YORK":"FALSE","brand":"BIG F'N DEAL","flavor":"Purple Drank","juiceID":357},{"FREDERICK":"TRUE","GETTYSBURG":"FALSE","LEMOYNE":"FALSE","YORK":"FALSE","brand":"BURST","flavor":"Duo Peach Raspberry","juiceID":362},{"FREDERICK":"TRUE","GETTYSBURG":"FALSE","LEMOYNE":"FALSE","YORK":"FALSE","brand":"BURST","flavor":"Citrus","juiceID":363},{"FREDERICK":"TRUE","GETTYSBURG":"FALSE","LEMOYNE":"FALSE","YORK":"FALSE","brand":"BURST","flavor":"Duo Apple Watermelon","juiceID":364},{"FREDERICK":"TRUE","GETTYSBURG":"FALSE","LEMOYNE":"FALSE","YORK":"FALSE","brand":"BURST","flavor":"Duo Kiwi Strawberry","juiceID":365},{"FREDERICK":"TRUE","GETTYSBURG":"FALSE","LEMOYNE":"FALSE","YORK":"FALSE","brand":"BURST","flavor":"Mango","juiceID":367},{"FREDERICK":"TRUE","GETTYSBURG":"FALSE","LEMOYNE":"FALSE","YORK":"FALSE","brand":"BURST","flavor":"Melon","juiceID":368},{"FREDERICK":"TRUE","GETTYSBURG":"FALSE","LEMOYNE":"FALSE","YORK":"FALSE","brand":"BURST","flavor":"Sher-Burst","juiceID":369},{"FREDERICK":"TRUE","GETTYSBURG":"FALSE","LEMOYNE":"FALSE","YORK":"FALSE","brand":"BURST","flavor":"Straw-burst","juiceID":370},{"FREDERICK":"TRUE","GETTYSBURG":"TRUE","LEMOYNE":"FALSE","YORK":"TRUE","brand":"CANDY KING","flavor":"Batch","juiceID":371},{"FREDERICK":"TRUE","GETTYSBURG":"FALSE","LEMOYNE":"FALSE","YORK":"FALSE","brand":"CANDY KING","flavor":"Blue Razz Bubble Gum","juiceID":372},{"FREDERICK":"TRUE","GETTYSBURG":"FALSE","LEMOYNE":"FALSE","YORK":"FALSE","brand":"CANDY KING","flavor":"Grape Bubble Gum","juiceID":373},{"FREDERICK":"TRUE","GETTYSBURG":"FALSE","LEMOYNE":"FALSE","YORK":"FALSE","brand":"CANDY KING","flavor":"Pink Lemonade Bubble Gum","juiceID":374},{"FREDERICK":"TRUE","GETTYSBURG":"TRUE","LEMOYNE":"FALSE","YORK":"TRUE","brand":"CANDY KING","flavor":"Pink Squares","juiceID":375},{"FREDERICK":"TRUE","GETTYSBURG":"TRUE","LEMOYNE":"FALSE","YORK":"FALSE","brand":"CANDY KING","flavor":"Strawberry Watermelon Bubble Gum","juiceID":376},{"FREDERICK":"TRUE","GETTYSBURG":"TRUE","LEMOYNE":"FALSE","YORK":"TRUE","brand":"CANDY KING","flavor":"Swedish","juiceID":377},{"FREDERICK":"TRUE","GETTYSBURG":"FALSE","LEMOYNE":"FALSE","YORK":"FALSE","brand":"CANDY KING","flavor":"Tropic","juiceID":378},{"FREDERICK":"TRUE","GETTYSBURG":"FALSE","LEMOYNE":"FALSE","YORK":"TRUE","brand":"CANDY KING","flavor":"Worms","juiceID":379},{"FREDERICK":"TRUE","GETTYSBURG":"FALSE","LEMOYNE":"FALSE","YORK":"FALSE","brand":"CHAIN VAPEZ","flavor":"Sauce","juiceID":380},{"FREDERICK":"TRUE","GETTYSBURG":"FALSE","LEMOYNE":"FALSE","YORK":"FALSE","brand":"CHAIN VAPEZ","flavor":"Sunrise Sherbet","juiceID":381},{"FREDERICK":"TRUE","GETTYSBURG":"FALSE","LEMOYNE":"FALSE","YORK":"FALSE","brand":"CHAIN VAPEZ","flavor":"XXX","juiceID":382},{"FREDERICK":"TRUE","GETTYSBURG":"FALSE","LEMOYNE":"FALSE","YORK":"FALSE","brand":"CHAIN VAPEZ","flavor":"XXX and Chill","juiceID":383},{"FREDERICK":"TRUE","GETTYSBURG":"TRUE","LEMOYNE":"FALSE","YORK":"FALSE","brand":"CHARLIE NOBLE","flavor":"Sollers Pointe","juiceID":385},{"FREDERICK":"TRUE","GETTYSBURG":"FALSE","LEMOYNE":"FALSE","YORK":"FALSE","brand":"CHUBBY BUBBLE","flavor":"Bubble Apple","juiceID":387},{"FREDERICK":"TRUE","GETTYSBURG":"FALSE","LEMOYNE":"FALSE","YORK":"FALSE","brand":"CHUBBY BUBBLE","flavor":"Bubble Strawberry","juiceID":388},{"FREDERICK":"TRUE","GETTYSBURG":"FALSE","LEMOYNE":"FALSE","YORK":"FALSE","brand":"COASTAL CLOUDS","flavor":"Mint","juiceID":404},{"FREDERICK":"TRUE","GETTYSBURG":"FALSE","LEMOYNE":"FALSE","YORK":"FALSE","brand":"COASTAL CLOUDS","flavor":"Sugar Nectarine","juiceID":408},{"FREDERICK":"TRUE","GETTYSBURG":"FALSE","LEMOYNE":"FALSE","YORK":"FALSE","brand":"COASTAL CLOUDS","flavor":"The Traveler","juiceID":409},{"FREDERICK":"TRUE","GETTYSBURG":"FALSE","LEMOYNE":"FALSE","YORK":"FALSE","brand":"COOKIE KING","flavor":"Dvnk","juiceID":414},{"FREDERICK":"TRUE","GETTYSBURG":"FALSE","LEMOYNE":"FALSE","YORK":"FALSE","brand":"COOKIE KING","flavor":"Lemon Wafers","juiceID":415},{"FREDERICK":"TRUE","GETTYSBURG":"FALSE","LEMOYNE":"FALSE","YORK":"FALSE","brand":"COUNTRY CLOUDS","flavor":"Banana bread pudding","juiceID":416},{"FREDERICK":"TRUE","GETTYSBURG":"FALSE","LEMOYNE":"FALSE","YORK":"FALSE","brand":"COUNTRY CLOUDS","flavor":"Chocolate Puddin'","juiceID":417},{"FREDERICK":"TRUE","GETTYSBURG":"TRUE","LEMOYNE":"FALSE","YORK":"TRUE","brand":"COUNTRY CLOUDS","flavor":"Corn Bread Puddin'","juiceID":418},{"FREDERICK":"TRUE","GETTYSBURG":"FALSE","LEMOYNE":"FALSE","YORK":"FALSE","brand":"COUNTRY CLOUDS","flavor":"lemon pudding pie","juiceID":419},{"FREDERICK":"TRUE","GETTYSBURG":"TRUE","LEMOYNE":"FALSE","YORK":"FALSE","brand":"CRUMBZ","flavor":"Flakey French Toast","juiceID":420},{"FREDERICK":"TRUE","GETTYSBURG":"FALSE","LEMOYNE":"FALSE","YORK":"FALSE","brand":"CRUMBZ","flavor":"Honeycrisp Apple","juiceID":421},{"FREDERICK":"TRUE","GETTYSBURG":"FALSE","LEMOYNE":"FALSE","YORK":"FALSE","brand":"CRUMBZ","flavor":"Short Straw","juiceID":422},{"FREDERICK":"TRUE","GETTYSBURG":"FALSE","LEMOYNE":"FALSE","YORK":"FALSE","brand":"CRUMBZ","flavor":"Vanilla","juiceID":423},{"FREDERICK":"TRUE","GETTYSBURG":"FALSE","LEMOYNE":"FALSE","YORK":"FALSE","brand":"CYCLOPS VAPOR","flavor":"Gryphon","juiceID":429},{"FREDERICK":"TRUE","GETTYSBURG":"FALSE","LEMOYNE":"FALSE","YORK":"FALSE","brand":"CYCLOPS VAPOR","flavor":"Phoenix","juiceID":431},{"FREDERICK":"TRUE","GETTYSBURG":"FALSE","LEMOYNE":"FALSE","YORK":"FALSE","brand":"CYCLOPS VAPOR","flavor":"Poseidon","juiceID":432},{"FREDERICK":"TRUE","GETTYSBURG":"TRUE","LEMOYNE":"FALSE","YORK":"TRUE","brand":"DEEP CUTS","flavor":"Blueberry Hill","juiceID":433},{"FREDERICK":"TRUE","GETTYSBURG":"TRUE","LEMOYNE":"FALSE","YORK":"TRUE","brand":"DEEP CUTS","flavor":"Dragonshake","juiceID":434},{"FREDERICK":"TRUE","GETTYSBURG":"TRUE","LEMOYNE":"FALSE","YORK":"TRUE","brand":"DEEP CUTS","flavor":"P.B. Party","juiceID":435},{"FREDERICK":"TRUE","GETTYSBURG":"TRUE","LEMOYNE":"FALSE","YORK":"TRUE","brand":"DEEP CUTS","flavor":"Psycho Cruller","juiceID":436},{"FREDERICK":"TRUE","GETTYSBURG":"TRUE","LEMOYNE":"FALSE","YORK":"TRUE","brand":"DEEP CUTS","flavor":"Strawberry Something","juiceID":437},{"FREDERICK":"TRUE","GETTYSBURG":"FALSE","LEMOYNE":"FALSE","YORK":"FALSE","brand":"DTF","flavor":"DTF Apple Love","juiceID":439},{"FREDERICK":"TRUE","GETTYSBURG":"FALSE","LEMOYNE":"FALSE","YORK":"FALSE","brand":"DTF","flavor":"Grape gobbler","juiceID":440},{"FREDERICK":"TRUE","GETTYSBURG":"FALSE","LEMOYNE":"FALSE","YORK":"FALSE","brand":"DTF","flavor":"Peachy Goodness","juiceID":441},{"FREDERICK":"TRUE","GETTYSBURG":"FALSE","LEMOYNE":"FALSE","YORK":"FALSE","brand":"FERRUM CITY","flavor":"Blue raspberry Fish","juiceID":445},{"FREDERICK":"TRUE","GETTYSBURG":"FALSE","LEMOYNE":"FALSE","YORK":"TRUE","brand":"FERRUM CITY","flavor":"Quickness","juiceID":453},{"FREDERICK":"TRUE","GETTYSBURG":"FALSE","LEMOYNE":"FALSE","YORK":"FALSE","brand":"FERRUM CITY","flavor":"Torched","juiceID":456},{"FREDERICK":"TRUE","GETTYSBURG":"FALSE","LEMOYNE":"FALSE","YORK":"FALSE","brand":"FRUITIA","flavor":"Apple Kiwi Crush","juiceID":467},{"FREDERICK":"TRUE","GETTYSBURG":"FALSE","LEMOYNE":"FALSE","YORK":"FALSE","brand":"FRUITIA","flavor":"Blood Orange Cactus Cooler","juiceID":468},{"FREDERICK":"TRUE","GETTYSBURG":"FALSE","LEMOYNE":"FALSE","YORK":"FALSE","brand":"FRUITIA","flavor":"Pineapple Citrus Twist","juiceID":469},{"FREDERICK":"TRUE","GETTYSBURG":"TRUE","LEMOYNE":"FALSE","YORK":"TRUE","brand":"GLAS","flavor":"Banana Cream Pie","juiceID":470},{"FREDERICK":"TRUE","GETTYSBURG":"TRUE","LEMOYNE":"FALSE","YORK":"TRUE","brand":"GLAS","flavor":"Blue razz","juiceID":471},{"FREDERICK":"TRUE","GETTYSBURG":"TRUE","LEMOYNE":"FALSE","YORK":"FALSE","brand":"GLAS","flavor":"Blueberry Cake","juiceID":472},{"FREDERICK":"TRUE","GETTYSBURG":"TRUE","LEMOYNE":"FALSE","YORK":"TRUE","brand":"GLAS","flavor":"Butterscotch Reserve","juiceID":473},{"FREDERICK":"TRUE","GETTYSBURG":"TRUE","LEMOYNE":"FALSE","YORK":"TRUE","brand":"GLAS","flavor":"Caribbean Punch","juiceID":474},{"FREDERICK":"TRUE","GETTYSBURG":"TRUE","LEMOYNE":"FALSE","YORK":"FALSE","brand":"GLAS","flavor":"Cool Melon","juiceID":475},{"FREDERICK":"TRUE","GETTYSBURG":"TRUE","LEMOYNE":"FALSE","YORK":"FALSE","brand":"GLAS","flavor":"Fizzy Lemonade","juiceID":476},{"FREDERICK":"TRUE","GETTYSBURG":"TRUE","LEMOYNE":"FALSE","YORK":"FALSE","brand":"GLAS","flavor":"Mango Tango","juiceID":477},{"FREDERICK":"TRUE","GETTYSBURG":"FALSE","LEMOYNE":"FALSE","YORK":"TRUE","brand":"GLAS","flavor":"OFT","juiceID":478},{"FREDERICK":"TRUE","GETTYSBURG":"FALSE","LEMOYNE":"FALSE","YORK":"TRUE","brand":"GLAS","flavor":"PBLS","juiceID":479},{"FREDERICK":"TRUE","GETTYSBURG":"TRUE","LEMOYNE":"FALSE","YORK":"FALSE","brand":"GLAS","flavor":"Pound Cake","juiceID":480},{"FREDERICK":"TRUE","GETTYSBURG":"FALSE","LEMOYNE":"FALSE","YORK":"FALSE","brand":"GLAS","flavor":"Strawberry Gummy","juiceID":481},{"FREDERICK":"TRUE","GETTYSBURG":"TRUE","LEMOYNE":"FALSE","YORK":"FALSE","brand":"GLAS","flavor":"Sugar Cookie","juiceID":482},{"FREDERICK":"TRUE","GETTYSBURG":"FALSE","LEMOYNE":"FALSE","YORK":"FALSE","brand":"HI DRIP","flavor":"Dew berry iced","juiceID":483},{"FREDERICK":"TRUE","GETTYSBURG":"FALSE","LEMOYNE":"FALSE","YORK":"FALSE","brand":"HI DRIP","flavor":"Guava Lava","juiceID":484},{"FREDERICK":"TRUE","GETTYSBURG":"FALSE","LEMOYNE":"FALSE","YORK":"FALSE","brand":"HI DRIP","flavor":"Guava lava iced","juiceID":485},{"FREDERICK":"TRUE","GETTYSBURG":"FALSE","LEMOYNE":"FALSE","YORK":"FALSE","brand":"HI DRIP","flavor":"Island orange","juiceID":486},{"FREDERICK":"TRUE","GETTYSBURG":"FALSE","LEMOYNE":"FALSE","YORK":"FALSE","brand":"HI DRIP","flavor":"Island orange iced","juiceID":487},{"FREDERICK":"TRUE","GETTYSBURG":"FALSE","LEMOYNE":"FALSE","YORK":"FALSE","brand":"HI DRIP","flavor":"Melon Patch","juiceID":488},{"FREDERICK":"TRUE","GETTYSBURG":"FALSE","LEMOYNE":"FALSE","YORK":"FALSE","brand":"HI DRIP","flavor":"Peachy Mango","juiceID":489},{"FREDERICK":"TRUE","GETTYSBURG":"FALSE","LEMOYNE":"FALSE","YORK":"FALSE","brand":"HI DRIP","flavor":"Peachy mango iced","juiceID":490},{"FREDERICK":"TRUE","GETTYSBURG":"TRUE","LEMOYNE":"FALSE","YORK":"FALSE","brand":"HOLY CANNOLI","flavor":"Blueberry Strudel","juiceID":491},{"FREDERICK":"TRUE","GETTYSBURG":"TRUE","LEMOYNE":"FALSE","YORK":"FALSE","brand":"HOLY CANNOLI","flavor":"French Toast","juiceID":492},{"FREDERICK":"TRUE","GETTYSBURG":"FALSE","LEMOYNE":"FALSE","YORK":"FALSE","brand":"HOLY CANNOLI","flavor":"Pebbled Cannoli","juiceID":493},{"FREDERICK":"TRUE","GETTYSBURG":"TRUE","LEMOYNE":"FALSE","YORK":"FALSE","brand":"HOLY CANNOLI","flavor":"Strawberry Cream","juiceID":494},{"FREDERICK":"TRUE","GETTYSBURG":"FALSE","LEMOYNE":"FALSE","YORK":"FALSE","brand":"HUMBLE","flavor":"Banana Bread","juiceID":495},{"FREDERICK":"TRUE","GETTYSBURG":"FALSE","LEMOYNE":"FALSE","YORK":"FALSE","brand":"HUMBLE","flavor":"Blue Raspberry Menthol","juiceID":496},{"FREDERICK":"TRUE","GETTYSBURG":"FALSE","LEMOYNE":"FALSE","YORK":"FALSE","brand":"HUMBLE","flavor":"Creamy Crunch","juiceID":497},{"FREDERICK":"TRUE","GETTYSBURG":"FALSE","LEMOYNE":"FALSE","YORK":"FALSE","brand":"HUMBLE","flavor":"Kiwi Berry Citrus","juiceID":498},{"FREDERICK":"TRUE","GETTYSBURG":"FALSE","LEMOYNE":"FALSE","YORK":"FALSE","brand":"HUMBLE","flavor":"Mango Passionfruit","juiceID":499},{"FREDERICK":"TRUE","GETTYSBURG":"FALSE","LEMOYNE":"FALSE","YORK":"FALSE","brand":"HUMBLE","flavor":"Strawberry Banana","juiceID":500},{"FREDERICK":"TRUE","GETTYSBURG":"FALSE","LEMOYNE":"FALSE","YORK":"FALSE","brand":"HUMBLE","flavor":"Toffee Vanilla Custard","juiceID":501},{"FREDERICK":"TRUE","GETTYSBURG":"FALSE","LEMOYNE":"FALSE","YORK":"FALSE","brand":"INNEVAPE","flavor":"Heisenberg","juiceID":506},{"FREDERICK":"TRUE","GETTYSBURG":"FALSE","LEMOYNE":"FALSE","YORK":"FALSE","brand":"IT'S PIXY","flavor":"Cucumber Watermelon","juiceID":510},{"FREDERICK":"TRUE","GETTYSBURG":"TRUE","LEMOYNE":"FALSE","YORK":"FALSE","brand":"JAM MONSTER","flavor":"Apple","juiceID":511},{"FREDERICK":"TRUE","GETTYSBURG":"FALSE","LEMOYNE":"FALSE","YORK":"TRUE","brand":"JAM MONSTER","flavor":"Grape","juiceID":514},{"FREDERICK":"TRUE","GETTYSBURG":"FALSE","LEMOYNE":"FALSE","YORK":"TRUE","brand":"JAM MONSTER","flavor":"PB Jam Banana","juiceID":515},{"FREDERICK":"TRUE","GETTYSBURG":"FALSE","LEMOYNE":"FALSE","YORK":"TRUE","brand":"JAM MONSTER","flavor":"PB Jam Grape","juiceID":516},{"FREDERICK":"TRUE","GETTYSBURG":"FALSE","LEMOYNE":"FALSE","YORK":"TRUE","brand":"JAM MONSTER","flavor":"PB Jam Strawberry","juiceID":517},{"FREDERICK":"TRUE","GETTYSBURG":"FALSE","LEMOYNE":"FALSE","YORK":"FALSE","brand":"JIMMY JUICEMAN","flavor":"French Raspberry","juiceID":520},{"FREDERICK":"TRUE","GETTYSBURG":"FALSE","LEMOYNE":"FALSE","YORK":"FALSE","brand":"JUICEMAN","flavor":"Unicorn Frappe","juiceID":550},{"FREDERICK":"TRUE","GETTYSBURG":"TRUE","LEMOYNE":"FALSE","YORK":"TRUE","brand":"KEEP IT 100","flavor":"Birthday Shake","juiceID":551},{"FREDERICK":"TRUE","GETTYSBURG":"TRUE","LEMOYNE":"FALSE","YORK":"FALSE","brand":"KEEP IT 100","flavor":"Blue Slushie","juiceID":552},{"FREDERICK":"TRUE","GETTYSBURG":"TRUE","LEMOYNE":"FALSE","YORK":"FALSE","brand":"KEEP IT 100","flavor":"Blue Slushie Tropical","juiceID":553},{"FREDERICK":"TRUE","GETTYSBURG":"FALSE","LEMOYNE":"FALSE","YORK":"FALSE","brand":"LOLLI DRIP","flavor":"Caramel Apple","juiceID":558},{"FREDERICK":"TRUE","GETTYSBURG":"FALSE","LEMOYNE":"FALSE","YORK":"FALSE","brand":"LOLLI DRIP","flavor":"Grapefruit","juiceID":559},{"FREDERICK":"TRUE","GETTYSBURG":"FALSE","LEMOYNE":"FALSE","YORK":"FALSE","brand":"LOLLI DRIP","flavor":"Watermelon","juiceID":560},{"FREDERICK":"TRUE","GETTYSBURG":"TRUE","LEMOYNE":"FALSE","YORK":"FALSE","brand":"LOST DREAMS","flavor":"NY Cheesecake","juiceID":561},{"FREDERICK":"TRUE","GETTYSBURG":"TRUE","LEMOYNE":"FALSE","YORK":"FALSE","brand":"LOST DREAMS","flavor":"Pebbles Cheesecake","juiceID":562},{"FREDERICK":"TRUE","GETTYSBURG":"FALSE","LEMOYNE":"FALSE","YORK":"FALSE","brand":"MIGHTY VAPORS","flavor":"Super Mint","juiceID":566},{"FREDERICK":"TRUE","GETTYSBURG":"TRUE","LEMOYNE":"FALSE","YORK":"FALSE","brand":"MR. FREEZE","flavor":"Cubano Tobacco","juiceID":568},{"FREDERICK":"TRUE","GETTYSBURG":"TRUE","LEMOYNE":"FALSE","YORK":"FALSE","brand":"MR. FREEZE","flavor":"Menthol Tobacco","juiceID":569},{"FREDERICK":"TRUE","GETTYSBURG":"TRUE","LEMOYNE":"FALSE","YORK":"TRUE","brand":"MR. FREEZE","flavor":"Vanilla Tobacco","juiceID":572},{"FREDERICK":"TRUE","GETTYSBURG":"TRUE","LEMOYNE":"FALSE","YORK":"FALSE","brand":"NAKED100","flavor":"Berry Very Cool","juiceID":573},{"FREDERICK":"TRUE","GETTYSBURG":"FALSE","LEMOYNE":"FALSE","YORK":"FALSE","brand":"NAKED100","flavor":"Melon(Polar Breeze)","juiceID":577},{"FREDERICK":"TRUE","GETTYSBURG":"FALSE","LEMOYNE":"FALSE","YORK":"FALSE","brand":"NAKED100","flavor":"Peachy Punch","juiceID":578},{"FREDERICK":"TRUE","GETTYSBURG":"FALSE","LEMOYNE":"FALSE","YORK":"FALSE","brand":"NAKED100","flavor":"Brain Freeze","juiceID":580},{"FREDERICK":"TRUE","GETTYSBURG":"FALSE","LEMOYNE":"FALSE","YORK":"FALSE","brand":"NOMS","flavor":"Artic wintergreen freeze","juiceID":581},{"FREDERICK":"TRUE","GETTYSBURG":"FALSE","LEMOYNE":"FALSE","YORK":"FALSE","brand":"NOMS","flavor":"Caramel butterscotch classic","juiceID":586},{"FREDERICK":"TRUE","GETTYSBURG":"FALSE","LEMOYNE":"FALSE","YORK":"FALSE","brand":"NOMS","flavor":"Pear green apple peach","juiceID":590},{"FREDERICK":"TRUE","GETTYSBURG":"FALSE","LEMOYNE":"FALSE","YORK":"TRUE","brand":"NOMS","flavor":"Phenomenon","juiceID":591},{"FREDERICK":"TRUE","GETTYSBURG":"FALSE","LEMOYNE":"FALSE","YORK":"TRUE","brand":"NOMS","flavor":"Stranomenon","juiceID":593},{"FREDERICK":"TRUE","GETTYSBURG":"FALSE","LEMOYNE":"FALSE","YORK":"TRUE","brand":"NOMS","flavor":"Watanomenon","juiceID":594},{"FREDERICK":"TRUE","GETTYSBURG":"FALSE","LEMOYNE":"FALSE","YORK":"FALSE","brand":"NOMS","flavor":"Waternom ice","juiceID":595},{"FREDERICK":"TRUE","GETTYSBURG":"FALSE","LEMOYNE":"FALSE","YORK":"TRUE","brand":"ONE HIT WONDER","flavor":"Magic Man","juiceID":600},{"FREDERICK":"TRUE","GETTYSBURG":"FALSE","LEMOYNE":"FALSE","YORK":"TRUE","brand":"ONE HIT WONDER","flavor":"My Man","juiceID":603},{"FREDERICK":"TRUE","GETTYSBURG":"FALSE","LEMOYNE":"FALSE","YORK":"FALSE","brand":"ONE HIT WONDER","flavor":"Rocket Man","juiceID":604},{"FREDERICK":"TRUE","GETTYSBURG":"FALSE","LEMOYNE":"FALSE","YORK":"TRUE","brand":"PACHA MAMA","flavor":"Huckleberry Pear Acai","juiceID":611},{"FREDERICK":"TRUE","GETTYSBURG":"FALSE","LEMOYNE":"FALSE","YORK":"FALSE","brand":"PACHA MAMA","flavor":"Passionfruit Raspberry Yuzu","juiceID":614},{"FREDERICK":"TRUE","GETTYSBURG":"FALSE","LEMOYNE":"FALSE","YORK":"FALSE","brand":"PRIMUS","flavor":"Limearita","juiceID":623},{"FREDERICK":"TRUE","GETTYSBURG":"FALSE","LEMOYNE":"FALSE","YORK":"FALSE","brand":"PRIMUS","flavor":"Prickly Pear","juiceID":624},{"FREDERICK":"TRUE","GETTYSBURG":"FALSE","LEMOYNE":"FALSE","YORK":"FALSE","brand":"PRIMUS","flavor":"Prickly Pear Ice","juiceID":625},{"FREDERICK":"TRUE","GETTYSBURG":"FALSE","LEMOYNE":"FALSE","YORK":"FALSE","brand":"PRIMUS","flavor":"Razzberry Rush","juiceID":626},{"FREDERICK":"TRUE","GETTYSBURG":"FALSE","LEMOYNE":"FALSE","YORK":"FALSE","brand":"PRIMUS","flavor":"Razzberry Rush Ice","juiceID":627},{"FREDERICK":"TRUE","GETTYSBURG":"FALSE","LEMOYNE":"FALSE","YORK":"FALSE","brand":"PROHIBITION","flavor":"First Thangs First","juiceID":629},{"FREDERICK":"TRUE","GETTYSBURG":"FALSE","LEMOYNE":"FALSE","YORK":"FALSE","brand":"PROHIBITION","flavor":"Sweet Thang","juiceID":632},{"FREDERICK":"TRUE","GETTYSBURG":"FALSE","LEMOYNE":"FALSE","YORK":"FALSE","brand":"PROHIBITION","flavor":"That New Thang","juiceID":633},{"FREDERICK":"TRUE","GETTYSBURG":"FALSE","LEMOYNE":"FALSE","YORK":"FALSE","brand":"PROHIBITION","flavor":"These Thangs Happen","juiceID":634},{"FREDERICK":"TRUE","GETTYSBURG":"TRUE","LEMOYNE":"FALSE","YORK":"FALSE","brand":"PROHIBITION","flavor":"White Lightning","juiceID":635},{"FREDERICK":"TRUE","GETTYSBURG":"FALSE","LEMOYNE":"FALSE","YORK":"FALSE","brand":"PROHIBITION","flavor":"White lightning ice","juiceID":636},{"FREDERICK":"TRUE","GETTYSBURG":"TRUE","LEMOYNE":"FALSE","YORK":"FALSE","brand":"REDS","flavor":"Mango","juiceID":642},{"FREDERICK":"TRUE","GETTYSBURG":"TRUE","LEMOYNE":"FALSE","YORK":"FALSE","brand":"REDS","flavor":"Mango ICE","juiceID":643},{"FREDERICK":"TRUE","GETTYSBURG":"FALSE","LEMOYNE":"FALSE","YORK":"FALSE","brand":"REDS","flavor":"Watermelon","juiceID":644},{"FREDERICK":"TRUE","GETTYSBURG":"FALSE","LEMOYNE":"FALSE","YORK":"FALSE","brand":"REDS","flavor":"Watermelon Ice","juiceID":645},{"FREDERICK":"TRUE","GETTYSBURG":"FALSE","LEMOYNE":"FALSE","YORK":"FALSE","brand":"RIOT","flavor":"Cherry Fizzle","juiceID":646},{"FREDERICK":"TRUE","GETTYSBURG":"FALSE","LEMOYNE":"FALSE","YORK":"FALSE","brand":"RIOT","flavor":"Rich Black Grape","juiceID":647},{"FREDERICK":"TRUE","GETTYSBURG":"FALSE","LEMOYNE":"FALSE","YORK":"FALSE","brand":"RIOT","flavor":"Sub Lime","juiceID":648},{"FREDERICK":"TRUE","GETTYSBURG":"FALSE","LEMOYNE":"FALSE","YORK":"TRUE","brand":"SAD BOY","flavor":"Butter Cookie","juiceID":650},{"FREDERICK":"TRUE","GETTYSBURG":"TRUE","LEMOYNE":"FALSE","YORK":"FALSE","brand":"SAD BOY","flavor":"Mango Blood","juiceID":653},{"FREDERICK":"TRUE","GETTYSBURG":"FALSE","LEMOYNE":"FALSE","YORK":"FALSE","brand":"SAD BOY","flavor":"Punch Berry Blood","juiceID":658},{"FREDERICK":"TRUE","GETTYSBURG":"FALSE","LEMOYNE":"FALSE","YORK":"FALSE","brand":"SAD BOY","flavor":"Punch Berry Blood Ice","juiceID":659},{"FREDERICK":"TRUE","GETTYSBURG":"FALSE","LEMOYNE":"FALSE","YORK":"FALSE","brand":"SAD BOY","flavor":"Tear Drops","juiceID":661},{"FREDERICK":"TRUE","GETTYSBURG":"TRUE","LEMOYNE":"FALSE","YORK":"TRUE","brand":"SALT BAE","flavor":"Green Apple ICE","juiceID":671},{"FREDERICK":"TRUE","GETTYSBURG":"FALSE","LEMOYNE":"FALSE","YORK":"FALSE","brand":"SALT BAE","flavor":"Iced Wintergreen","juiceID":673},{"FREDERICK":"TRUE","GETTYSBURG":"FALSE","LEMOYNE":"FALSE","YORK":"FALSE","brand":"SKWEZED","flavor":"Banana","juiceID":679},{"FREDERICK":"TRUE","GETTYSBURG":"FALSE","LEMOYNE":"FALSE","YORK":"FALSE","brand":"SKWEZED","flavor":"Banana Ice","juiceID":680},{"FREDERICK":"TRUE","GETTYSBURG":"FALSE","LEMOYNE":"FALSE","YORK":"FALSE","brand":"SOLACE","flavor":"Cool Mango","juiceID":681},{"FREDERICK":"TRUE","GETTYSBURG":"TRUE","LEMOYNE":"FALSE","YORK":"TRUE","brand":"SORBET POP","flavor":"Peach Mango","juiceID":685},{"FREDERICK":"TRUE","GETTYSBURG":"TRUE","LEMOYNE":"FALSE","YORK":"TRUE","brand":"SORBET POP","flavor":"Pineapple Kiwi Dragonfruit","juiceID":686},{"FREDERICK":"TRUE","GETTYSBURG":"TRUE","LEMOYNE":"FALSE","YORK":"TRUE","brand":"SORBET POP","flavor":"StrawLemon","juiceID":687},{"FREDERICK":"TRUE","GETTYSBURG":"TRUE","LEMOYNE":"FALSE","YORK":"TRUE","brand":"SORBET POP","flavor":"Tangerine Lime","juiceID":688},{"FREDERICK":"TRUE","GETTYSBURG":"FALSE","LEMOYNE":"FALSE","YORK":"TRUE","brand":"THE FINEST","flavor":"Banana Honey","juiceID":692},{"FREDERICK":"TRUE","GETTYSBURG":"FALSE","LEMOYNE":"FALSE","YORK":"FALSE","brand":"THE FINEST","flavor":"Green Apple Citrus","juiceID":698},{"FREDERICK":"TRUE","GETTYSBURG":"TRUE","LEMOYNE":"FALSE","YORK":"TRUE","brand":"THE FINEST","flavor":"Lemon Lush","juiceID":699},{"FREDERICK":"TRUE","GETTYSBURG":"FALSE","LEMOYNE":"FALSE","YORK":"FALSE","brand":"THE FINEST","flavor":"Lychee Dragon","juiceID":700},{"FREDERICK":"TRUE","GETTYSBURG":"FALSE","LEMOYNE":"FALSE","YORK":"FALSE","brand":"THE FINEST","flavor":"Russian Cream","juiceID":703},{"FREDERICK":"TRUE","GETTYSBURG":"TRUE","LEMOYNE":"FALSE","YORK":"FALSE","brand":"THE ONE","flavor":"Vanilla Custard Donut","juiceID":711},{"FREDERICK":"TRUE","GETTYSBURG":"TRUE","LEMOYNE":"FALSE","YORK":"FALSE","brand":"TRANSISTOR","flavor":"Babyclouds","juiceID":712},{"FREDERICK":"TRUE","GETTYSBURG":"TRUE","LEMOYNE":"FALSE","YORK":"TRUE","brand":"TRANSISTOR","flavor":"Galactic Milk","juiceID":716},{"FREDERICK":"TRUE","GETTYSBURG":"FALSE","LEMOYNE":"FALSE","YORK":"FALSE","brand":"TRANSISTOR","flavor":"Lemon Drop","juiceID":718},{"FREDERICK":"TRUE","GETTYSBURG":"TRUE","LEMOYNE":"FALSE","YORK":"FALSE","brand":"TWIST","flavor":"Cookie Twist Banana Oatmeal Cookie","juiceID":724},{"FREDERICK":"TRUE","GETTYSBURG":"TRUE","LEMOYNE":"FALSE","YORK":"FALSE","brand":"TWIST","flavor":"Cookie Twist Frosted Sugar Cookie","juiceID":725},{"FREDERICK":"TRUE","GETTYSBURG":"TRUE","LEMOYNE":"FALSE","YORK":"FALSE","brand":"TWIST","flavor":"Cookie Twist Strawberry Honey Graham","juiceID":726},{"FREDERICK":"TRUE","GETTYSBURG":"TRUE","LEMOYNE":"FALSE","YORK":"FALSE","brand":"TWIST","flavor":"Fruit Twist Tropical Pucker Punch","juiceID":727},{"FREDERICK":"TRUE","GETTYSBURG":"TRUE","LEMOYNE":"FALSE","YORK":"FALSE","brand":"TWIST","flavor":"Honey Twist Golden Honey Bomb","juiceID":728},{"FREDERICK":"TRUE","GETTYSBURG":"TRUE","LEMOYNE":"FALSE","YORK":"FALSE","brand":"TWIST","flavor":"Honeydew Melon Chew","juiceID":729},{"FREDERICK":"TRUE","GETTYSBURG":"TRUE","LEMOYNE":"FALSE","YORK":"FALSE","brand":"TWIST","flavor":"Iced Pink Punch Lemonade","juiceID":730},{"FREDERICK":"TRUE","GETTYSBURG":"TRUE","LEMOYNE":"FALSE","YORK":"FALSE","brand":"TWIST","flavor":"Lemon Twist Iced Pink Punch","juiceID":731},{"FREDERICK":"TRUE","GETTYSBURG":"FALSE","LEMOYNE":"FALSE","YORK":"FALSE","brand":"TWIST","flavor":"Lemon Twist Pink Punch Lemonade","juiceID":732},{"FREDERICK":"TRUE","GETTYSBURG":"FALSE","LEMOYNE":"FALSE","YORK":"FALSE","brand":"TWIST","flavor":"Lemon Twist Strawberry Mason","juiceID":733},{"FREDERICK":"TRUE","GETTYSBURG":"TRUE","LEMOYNE":"FALSE","YORK":"FALSE","brand":"TWIST","flavor":"Lemon Twist Wild Watermelon","juiceID":734},{"FREDERICK":"TRUE","GETTYSBURG":"TRUE","LEMOYNE":"FALSE","YORK":"FALSE","brand":"TWIST","flavor":"Melon Twist Chilled Melon Remix","juiceID":735},{"FREDERICK":"TRUE","GETTYSBURG":"TRUE","LEMOYNE":"FALSE","YORK":"FALSE","brand":"TWIST","flavor":"Melon Twist Honeydew Melon Chew","juiceID":736},{"FREDERICK":"TRUE","GETTYSBURG":"TRUE","LEMOYNE":"FALSE","YORK":"FALSE","brand":"TWIST","flavor":"Melon Twist Watermelon Madness","juiceID":737},{"FREDERICK":"TRUE","GETTYSBURG":"TRUE","LEMOYNE":"FALSE","YORK":"FALSE","brand":"TWIST","flavor":"Pink Punch Lemonade","juiceID":738},{"FREDERICK":"TRUE","GETTYSBURG":"TRUE","LEMOYNE":"FALSE","YORK":"TRUE","brand":"TWIST","flavor":"Strawberry Crush Ice","juiceID":740},{"FREDERICK":"TRUE","GETTYSBURG":"TRUE","LEMOYNE":"FALSE","YORK":"FALSE","brand":"TWIST","flavor":"Mixed Berry Lemonade","juiceID":741},{"FREDERICK":"TRUE","GETTYSBURG":"TRUE","LEMOYNE":"FALSE","YORK":"FALSE","brand":"TWIST","flavor":"Watermelon Madness","juiceID":742},{"FREDERICK":"TRUE","GETTYSBURG":"FALSE","LEMOYNE":"FALSE","YORK":"FALSE","brand":"VAPETASIA","flavor":"Vapetasia Killer Kustard","juiceID":744},{"FREDERICK":"TRUE","GETTYSBURG":"FALSE","LEMOYNE":"FALSE","YORK":"FALSE","brand":"WATERMELON FIESTA","flavor":"Sweet & Sour Watermelon","juiceID":745},{"FREDERICK":"FALSE","GETTYSBURG":"TRUE","LEMOYNE":"FALSE","YORK":"FALSE","brand":"AIR FACTORY","flavor":"Berry Rush","juiceID":746},{"FREDERICK":"FALSE","GETTYSBURG":"TRUE","LEMOYNE":"FALSE","YORK":"FALSE","brand":"ANVIL","flavor":"Torch","juiceID":750},{"FREDERICK":"FALSE","GETTYSBURG":"TRUE","LEMOYNE":"FALSE","YORK":"FALSE","brand":"BAD DRIP","flavor":"Lemon Tart","juiceID":754},{"FREDERICK":"FALSE","GETTYSBURG":"TRUE","LEMOYNE":"FALSE","YORK":"FALSE","brand":"BARISTA BREW","flavor":"Salted caramel macchiato","juiceID":755},{"FREDERICK":"FALSE","GETTYSBURG":"TRUE","LEMOYNE":"FALSE","YORK":"FALSE","brand":"BREWED AWAKENING","flavor":"Cinnamon Vanilla chai tea","juiceID":769},{"FREDERICK":"FALSE","GETTYSBURG":"TRUE","LEMOYNE":"FALSE","YORK":"FALSE","brand":"BREWED AWAKENING","flavor":"Mocha Hazlenut coffee","juiceID":770},{"FREDERICK":"FALSE","GETTYSBURG":"TRUE","LEMOYNE":"FALSE","YORK":"TRUE","brand":"CANDY KING","flavor":"Berry Dweebz","juiceID":772},{"FREDERICK":"FALSE","GETTYSBURG":"TRUE","LEMOYNE":"FALSE","YORK":"FALSE","brand":"CASSADAGA","flavor":"Cannoli be cookies","juiceID":778},{"FREDERICK":"FALSE","GETTYSBURG":"TRUE","LEMOYNE":"FALSE","YORK":"FALSE","brand":"CHARLIE NOBLE","flavor":"Captain","juiceID":783},{"FREDERICK":"FALSE","GETTYSBURG":"TRUE","LEMOYNE":"FALSE","YORK":"FALSE","brand":"DOCTOR BIG VAPES","flavor":"Carnival Apple","juiceID":818},{"FREDERICK":"FALSE","GETTYSBURG":"TRUE","LEMOYNE":"FALSE","YORK":"FALSE","brand":"DOCTOR BIG VAPES","flavor":"Wildberry Limeade","juiceID":819},{"FREDERICK":"FALSE","GETTYSBURG":"TRUE","LEMOYNE":"FALSE","YORK":"FALSE","brand":"FERRUM CITY","flavor":"Booberry","juiceID":823},{"FREDERICK":"FALSE","GETTYSBURG":"TRUE","LEMOYNE":"FALSE","YORK":"FALSE","brand":"FERRUM CITY","flavor":"The quickness","juiceID":830},{"FREDERICK":"FALSE","GETTYSBURG":"TRUE","LEMOYNE":"FALSE","YORK":"FALSE","brand":"FROZEN FRUIT MONSTER","flavor":"Orange passionfruit guava Ice","juiceID":835},{"FREDERICK":"FALSE","GETTYSBURG":"TRUE","LEMOYNE":"FALSE","YORK":"TRUE","brand":"FROZEN FRUIT MONSTER","flavor":"Strawberry kiwi Pomegrante Ice","juiceID":836},{"FREDERICK":"FALSE","GETTYSBURG":"TRUE","LEMOYNE":"FALSE","YORK":"FALSE","brand":"INNEVAPE","flavor":"Chill Out","juiceID":859},{"FREDERICK":"FALSE","GETTYSBURG":"TRUE","LEMOYNE":"FALSE","YORK":"FALSE","brand":"INNEVAPE","flavor":"Innevape Chill Out","juiceID":860},{"FREDERICK":"FALSE","GETTYSBURG":"TRUE","LEMOYNE":"FALSE","YORK":"FALSE","brand":"INNEVAPE","flavor":"TNT","juiceID":861},{"FREDERICK":"FALSE","GETTYSBURG":"TRUE","LEMOYNE":"FALSE","YORK":"TRUE","brand":"INNEVAPE","flavor":"TNT Menthol","juiceID":862},{"FREDERICK":"FALSE","GETTYSBURG":"TRUE","LEMOYNE":"FALSE","YORK":"FALSE","brand":"JAM MONSTER","flavor":"Banana","juiceID":866},{"FREDERICK":"FALSE","GETTYSBURG":"TRUE","LEMOYNE":"FALSE","YORK":"FALSE","brand":"JUICE HEAD FREEZE","flavor":"Blueberry Lemon Freeze","juiceID":878},{"FREDERICK":"FALSE","GETTYSBURG":"TRUE","LEMOYNE":"FALSE","YORK":"FALSE","brand":"JUICE HEAD FREEZE","flavor":"Peach Pear Freeze","juiceID":879},{"FREDERICK":"FALSE","GETTYSBURG":"TRUE","LEMOYNE":"FALSE","YORK":"FALSE","brand":"JUICE HEAD FREEZE","flavor":"Pineapple Grapefruit Freeze","juiceID":880},{"FREDERICK":"FALSE","GETTYSBURG":"TRUE","LEMOYNE":"FALSE","YORK":"FALSE","brand":"JUICE HEAD FREEZE","flavor":"Strawberry Kiwi Freeze","juiceID":881},{"FREDERICK":"FALSE","GETTYSBURG":"TRUE","LEMOYNE":"FALSE","YORK":"FALSE","brand":"JUICE HEAD FREEZE","flavor":"Watermelon Lime Freeze","juiceID":882},{"FREDERICK":"FALSE","GETTYSBURG":"TRUE","LEMOYNE":"FALSE","YORK":"FALSE","brand":"KEEP IT 100","flavor":"OG Krunch","juiceID":904},{"FREDERICK":"FALSE","GETTYSBURG":"TRUE","LEMOYNE":"FALSE","YORK":"FALSE","brand":"KEEP IT 100","flavor":"Peachy Punch","juiceID":905},{"FREDERICK":"FALSE","GETTYSBURG":"TRUE","LEMOYNE":"FALSE","YORK":"FALSE","brand":"KEEP IT 100","flavor":"Pink Burst","juiceID":906},{"FREDERICK":"FALSE","GETTYSBURG":"TRUE","LEMOYNE":"FALSE","YORK":"TRUE","brand":"KEEP IT 100","flavor":"Tropical Blast","juiceID":907},{"FREDERICK":"FALSE","GETTYSBURG":"TRUE","LEMOYNE":"FALSE","YORK":"FALSE","brand":"KILLA FRUITS","flavor":"Raspberry Black Cherry Lemon","juiceID":909},{"FREDERICK":"FALSE","GETTYSBURG":"TRUE","LEMOYNE":"FALSE","YORK":"FALSE","brand":"KILLA FRUITS","flavor":"Watermelon Nectarine","juiceID":912},{"FREDERICK":"FALSE","GETTYSBURG":"TRUE","LEMOYNE":"FALSE","YORK":"FALSE","brand":"LOLLI DRIPS","flavor":"Caramel Apple","juiceID":914},{"FREDERICK":"FALSE","GETTYSBURG":"TRUE","LEMOYNE":"FALSE","YORK":"FALSE","brand":"LOLLI DRIPS","flavor":"Grapefruit","juiceID":915},{"FREDERICK":"FALSE","GETTYSBURG":"TRUE","LEMOYNE":"FALSE","YORK":"FALSE","brand":"NAKED100","flavor":"Maui sun","juiceID":931},{"FREDERICK":"FALSE","GETTYSBURG":"TRUE","LEMOYNE":"FALSE","YORK":"FALSE","brand":"NAKED100","flavor":"Polar Breeze","juiceID":932},{"FREDERICK":"FALSE","GETTYSBURG":"TRUE","LEMOYNE":"FALSE","YORK":"FALSE","brand":"OHM BOY","flavor":"Heads","juiceID":940},{"FREDERICK":"FALSE","GETTYSBURG":"TRUE","LEMOYNE":"FALSE","YORK":"FALSE","brand":"OHM BOY","flavor":"Punch","juiceID":941},{"FREDERICK":"FALSE","GETTYSBURG":"TRUE","LEMOYNE":"FALSE","YORK":"FALSE","brand":"OHM BOY","flavor":"Tropical","juiceID":942},{"FREDERICK":"FALSE","GETTYSBURG":"TRUE","LEMOYNE":"FALSE","YORK":"FALSE","brand":"ONE HIT WONDER","flavor":"Muffin man apple","juiceID":945},{"FREDERICK":"FALSE","GETTYSBURG":"TRUE","LEMOYNE":"FALSE","YORK":"FALSE","brand":"ONE HIT WONDER","flavor":"Muffin man strawberry","juiceID":946},{"FREDERICK":"FALSE","GETTYSBURG":"TRUE","LEMOYNE":"FALSE","YORK":"FALSE","brand":"PB & JAM MONSTER","flavor":"Banana Peanut butter","juiceID":949},{"FREDERICK":"FALSE","GETTYSBURG":"TRUE","LEMOYNE":"FALSE","YORK":"FALSE","brand":"PB & JAM MONSTER","flavor":"Grape jam Peanut butter","juiceID":950},{"FREDERICK":"FALSE","GETTYSBURG":"TRUE","LEMOYNE":"FALSE","YORK":"FALSE","brand":"PB & JAM MONSTER","flavor":"Strawberry Peanut butter","juiceID":951},{"FREDERICK":"FALSE","GETTYSBURG":"TRUE","LEMOYNE":"FALSE","YORK":"FALSE","brand":"Propaganda","flavor":"America","juiceID":956},{"FREDERICK":"FALSE","GETTYSBURG":"TRUE","LEMOYNE":"FALSE","YORK":"TRUE","brand":"SAD BOY","flavor":"Rainbow Blood","juiceID":969},{"FREDERICK":"FALSE","GETTYSBURG":"TRUE","LEMOYNE":"FALSE","YORK":"FALSE","brand":"THE BEARD","flavor":"No. 32","juiceID":991},{"FREDERICK":"FALSE","GETTYSBURG":"TRUE","LEMOYNE":"FALSE","YORK":"FALSE","brand":"THE BEARD","flavor":"No. 5","juiceID":992},{"FREDERICK":"FALSE","GETTYSBURG":"TRUE","LEMOYNE":"FALSE","YORK":"FALSE","brand":"TRANSISTOR","flavor":"Butterscotch Bourbon Blend","juiceID":1006},{"FREDERICK":"FALSE","GETTYSBURG":"TRUE","LEMOYNE":"FALSE","YORK":"FALSE","brand":"TWIST","flavor":"Frosted Sugar Cookie","juiceID":1019},{"FREDERICK":"FALSE","GETTYSBURG":"TRUE","LEMOYNE":"FALSE","YORK":"FALSE","brand":"TWIST","flavor":"Menthol No. 1","juiceID":1030},{"FREDERICK":"FALSE","GETTYSBURG":"TRUE","LEMOYNE":"FALSE","YORK":"FALSE","brand":"TWIST","flavor":"Pink Punch Iced","juiceID":1032},{"FREDERICK":"FALSE","GETTYSBURG":"TRUE","LEMOYNE":"FALSE","YORK":"FALSE","brand":"TWIST","flavor":"Strawberry Honey Graham","juiceID":1035},{"FREDERICK":"FALSE","GETTYSBURG":"TRUE","LEMOYNE":"FALSE","YORK":"FALSE","brand":"TWIST","flavor":"Tropical Pucker Punch","juiceID":1036},{"FREDERICK":"FALSE","GETTYSBURG":"TRUE","LEMOYNE":"FALSE","YORK":"FALSE","brand":"TWIST","flavor":"Twisted Mixed Berry Lemonade","juiceID":1037},{"FREDERICK":"FALSE","GETTYSBURG":"TRUE","LEMOYNE":"FALSE","YORK":"FALSE","brand":"VAPETASIA","flavor":"Killer Kustard strawberry","juiceID":1040},{"FREDERICK":"FALSE","GETTYSBURG":"FALSE","LEMOYNE":"FALSE","YORK":"TRUE","brand":"FROZEN FRUIT MONSTER","flavor":"Strawberry Banana Ice","juiceID":1119},{"FREDERICK":"FALSE","GETTYSBURG":"FALSE","LEMOYNE":"FALSE","YORK":"TRUE","brand":"HUMBLE","flavor":"American Dream","juiceID":1133},{"FREDERICK":"FALSE","GETTYSBURG":"FALSE","LEMOYNE":"FALSE","YORK":"TRUE","brand":"HUMBLE","flavor":"Berry Blow Doe","juiceID":1134},{"FREDERICK":"FALSE","GETTYSBURG":"FALSE","LEMOYNE":"FALSE","YORK":"TRUE","brand":"HUMBLE","flavor":"Blue Slushie","juiceID":1135},{"FREDERICK":"FALSE","GETTYSBURG":"FALSE","LEMOYNE":"FALSE","YORK":"TRUE","brand":"HUMBLE","flavor":"Donkey Kahn","juiceID":1136},{"FREDERICK":"FALSE","GETTYSBURG":"FALSE","LEMOYNE":"FALSE","YORK":"TRUE","brand":"HUMBLE","flavor":"Fruit Punch","juiceID":1137},{"FREDERICK":"FALSE","GETTYSBURG":"FALSE","LEMOYNE":"FALSE","YORK":"TRUE","brand":"HUMBLE","flavor":"Guava Kahn","juiceID":1138},{"FREDERICK":"FALSE","GETTYSBURG":"FALSE","LEMOYNE":"FALSE","YORK":"TRUE","brand":"HUMBLE","flavor":"Hop Scotch","juiceID":1139},{"FREDERICK":"FALSE","GETTYSBURG":"FALSE","LEMOYNE":"FALSE","YORK":"TRUE","brand":"HUMBLE","flavor":"Humble Crumble","juiceID":1140},{"FREDERICK":"FALSE","GETTYSBURG":"FALSE","LEMOYNE":"FALSE","YORK":"TRUE","brand":"HUMBLE","flavor":"Peach Pleasure","juiceID":1141},{"FREDERICK":"FALSE","GETTYSBURG":"FALSE","LEMOYNE":"FALSE","YORK":"TRUE","brand":"HUMBLE","flavor":"Pee Wee Kiwi","juiceID":1142},{"FREDERICK":"FALSE","GETTYSBURG":"FALSE","LEMOYNE":"FALSE","YORK":"TRUE","brand":"HUMBLE","flavor":"Smash Mouth","juiceID":1143},{"FREDERICK":"FALSE","GETTYSBURG":"FALSE","LEMOYNE":"FALSE","YORK":"TRUE","brand":"HUMBLE","flavor":"Sweater Puppets","juiceID":1144},{"FREDERICK":"FALSE","GETTYSBURG":"FALSE","LEMOYNE":"FALSE","YORK":"TRUE","brand":"HUMBLE","flavor":"VTR","juiceID":1145},{"FREDERICK":"FALSE","GETTYSBURG":"FALSE","LEMOYNE":"FALSE","YORK":"TRUE","brand":"INNEVAPE","flavor":"TNT Tobacco","juiceID":1151},{"FREDERICK":"FALSE","GETTYSBURG":"FALSE","LEMOYNE":"FALSE","YORK":"TRUE","brand":"KEEP IT 100","flavor":"Mint","juiceID":1191},{"FREDERICK":"FALSE","GETTYSBURG":"FALSE","LEMOYNE":"FALSE","YORK":"TRUE","brand":"KEEP IT 100","flavor":"OG Blue (Blue Slushie)","juiceID":1192},{"FREDERICK":"FALSE","GETTYSBURG":"FALSE","LEMOYNE":"FALSE","YORK":"TRUE","brand":"KEEP IT 100","flavor":"OG Crunch (Krunchy Squares)","juiceID":1193},{"FREDERICK":"FALSE","GETTYSBURG":"FALSE","LEMOYNE":"FALSE","YORK":"TRUE","brand":"KEEP IT 100","flavor":"Tropical Blue Razz","juiceID":1197},{"FREDERICK":"FALSE","GETTYSBURG":"FALSE","LEMOYNE":"FALSE","YORK":"TRUE","brand":"LEMONADE MONSTER","flavor":"Blueberry Lemonade","juiceID":1198},{"FREDERICK":"FALSE","GETTYSBURG":"FALSE","LEMOYNE":"FALSE","YORK":"TRUE","brand":"LEMONADE MONSTER","flavor":"Pink Lemonade","juiceID":1199},{"FREDERICK":"FALSE","GETTYSBURG":"FALSE","LEMOYNE":"FALSE","YORK":"TRUE","brand":"LEMONADE MONSTER","flavor":"Strawberry Lemonade","juiceID":1200},{"FREDERICK":"FALSE","GETTYSBURG":"FALSE","LEMOYNE":"FALSE","YORK":"TRUE","brand":"LEMONADE MONSTER","flavor":"Watermelon Lemonade","juiceID":1201},{"FREDERICK":"FALSE","GETTYSBURG":"FALSE","LEMOYNE":"FALSE","YORK":"TRUE","brand":"MRKT PLCE","flavor":"Fuji Pear Mangoberry","juiceID":1208},{"FREDERICK":"FALSE","GETTYSBURG":"FALSE","LEMOYNE":"FALSE","YORK":"TRUE","brand":"MRKT PLCE","flavor":"Watermelon Hula Berry Lime","juiceID":1209},{"FREDERICK":"FALSE","GETTYSBURG":"FALSE","LEMOYNE":"FALSE","YORK":"TRUE","brand":"NOMS","flavor":"Caramel Butterscotch Reserve","juiceID":1220},{"FREDERICK":"FALSE","GETTYSBURG":"FALSE","LEMOYNE":"FALSE","YORK":"TRUE","brand":"NOMS","flavor":"Lychee Cherry Blossom Raspberry","juiceID":1224},{"FREDERICK":"FALSE","GETTYSBURG":"FALSE","LEMOYNE":"FALSE","YORK":"TRUE","brand":"NOMS","flavor":"Strawnomenon ICE","juiceID":1228},{"FREDERICK":"FALSE","GETTYSBURG":"FALSE","LEMOYNE":"FALSE","YORK":"TRUE","brand":"POD JUICE","flavor":"Bangin' Blue Razz","juiceID":1251},{"FREDERICK":"FALSE","GETTYSBURG":"FALSE","LEMOYNE":"FALSE","YORK":"TRUE","brand":"POD JUICE","flavor":"Bangin' Blue Razz Chilled","juiceID":1252},{"FREDERICK":"FALSE","GETTYSBURG":"FALSE","LEMOYNE":"FALSE","YORK":"TRUE","brand":"POD JUICE","flavor":"Blue Razz Ice","juiceID":1253},{"FREDERICK":"FALSE","GETTYSBURG":"FALSE","LEMOYNE":"FALSE","YORK":"TRUE","brand":"POD JUICE","flavor":"Blueberry Muffin","juiceID":1254},{"FREDERICK":"FALSE","GETTYSBURG":"FALSE","LEMOYNE":"FALSE","YORK":"TRUE","brand":"POD JUICE","flavor":"Cola Ice","juiceID":1255},{"FREDERICK":"FALSE","GETTYSBURG":"FALSE","LEMOYNE":"FALSE","YORK":"TRUE","brand":"POD JUICE","flavor":"Cookies & Cream","juiceID":1256},{"FREDERICK":"FALSE","GETTYSBURG":"FALSE","LEMOYNE":"FALSE","YORK":"TRUE","brand":"POD JUICE","flavor":"Cotton Carnival","juiceID":1257},{"FREDERICK":"FALSE","GETTYSBURG":"FALSE","LEMOYNE":"FALSE","YORK":"TRUE","brand":"POD JUICE","flavor":"Jewel Mint","juiceID":1258},{"FREDERICK":"FALSE","GETTYSBURG":"FALSE","LEMOYNE":"FALSE","YORK":"TRUE","brand":"POD JUICE","flavor":"Jewel Tobacco","juiceID":1259},{"FREDERICK":"FALSE","GETTYSBURG":"FALSE","LEMOYNE":"FALSE","YORK":"TRUE","brand":"POD JUICE","flavor":"Juicy Apple","juiceID":1260},{"FREDERICK":"FALSE","GETTYSBURG":"FALSE","LEMOYNE":"FALSE","YORK":"TRUE","brand":"POD JUICE","flavor":"Lemon Brulee","juiceID":1261},{"FREDERICK":"FALSE","GETTYSBURG":"FALSE","LEMOYNE":"FALSE","YORK":"TRUE","brand":"POD JUICE","flavor":"Lemon Sugar Cookie","juiceID":1262},{"FREDERICK":"FALSE","GETTYSBURG":"FALSE","LEMOYNE":"FALSE","YORK":"TRUE","brand":"POD JUICE","flavor":"Loops","juiceID":1263},{"FREDERICK":"FALSE","GETTYSBURG":"FALSE","LEMOYNE":"FALSE","YORK":"TRUE","brand":"POD JUICE","flavor":"Orange Soda","juiceID":1264},{"FREDERICK":"FALSE","GETTYSBURG":"FALSE","LEMOYNE":"FALSE","YORK":"TRUE","brand":"POD JUICE","flavor":"Strawberry Apple Watermelon","juiceID":1265},{"FREDERICK":"FALSE","GETTYSBURG":"FALSE","LEMOYNE":"FALSE","YORK":"TRUE","brand":"POD JUICE","flavor":"Strawberry Banana","juiceID":1266},{"FREDERICK":"FALSE","GETTYSBURG":"FALSE","LEMOYNE":"FALSE","YORK":"TRUE","brand":"POD JUICE","flavor":"Strawberry Banana Ice","juiceID":1267},{"FREDERICK":"FALSE","GETTYSBURG":"FALSE","LEMOYNE":"FALSE","YORK":"TRUE","brand":"POD JUICE","flavor":"Strawberry Dream","juiceID":1268},{"FREDERICK":"FALSE","GETTYSBURG":"FALSE","LEMOYNE":"FALSE","YORK":"TRUE","brand":"POD JUICE","flavor":"Strawberry Kiwi","juiceID":1269},{"FREDERICK":"FALSE","GETTYSBURG":"FALSE","LEMOYNE":"FALSE","YORK":"TRUE","brand":"POD JUICE","flavor":"Strawberry Kiwi Iced","juiceID":1270},{"FREDERICK":"FALSE","GETTYSBURG":"FALSE","LEMOYNE":"FALSE","YORK":"TRUE","brand":"POD JUICE","flavor":"Strawberry Lemonade","juiceID":1271},{"FREDERICK":"FALSE","GETTYSBURG":"FALSE","LEMOYNE":"FALSE","YORK":"TRUE","brand":"POD JUICE","flavor":"Strawberry Pink Burst","juiceID":1272},{"FREDERICK":"FALSE","GETTYSBURG":"FALSE","LEMOYNE":"FALSE","YORK":"TRUE","brand":"POD JUICE","flavor":"Strawberry Watermelon","juiceID":1273},{"FREDERICK":"FALSE","GETTYSBURG":"FALSE","LEMOYNE":"FALSE","YORK":"TRUE","brand":"POD JUICE","flavor":"Vanilla Custard Tobacco","juiceID":1274},{"FREDERICK":"FALSE","GETTYSBURG":"FALSE","LEMOYNE":"FALSE","YORK":"TRUE","brand":"PROHIBITION","flavor":"White Lightening Ice","juiceID":1279},{"FREDERICK":"FALSE","GETTYSBURG":"FALSE","LEMOYNE":"FALSE","YORK":"TRUE","brand":"SUICIDE BUNNY","flavor":"Mother's Milk","juiceID":1302},{"FREDERICK":"FALSE","GETTYSBURG":"FALSE","LEMOYNE":"FALSE","YORK":"TRUE","brand":"THE GRAHAM","flavor":"Blueberry","juiceID":1317},{"FREDERICK":"FALSE","GETTYSBURG":"FALSE","LEMOYNE":"FALSE","YORK":"TRUE","brand":"THE GRAHAM","flavor":"Original","juiceID":1318},{"FREDERICK":"FALSE","GETTYSBURG":"FALSE","LEMOYNE":"FALSE","YORK":"TRUE","brand":"THE GRAHAM","flavor":"Strawberry","juiceID":1319},{"FREDERICK":"FALSE","GETTYSBURG":"FALSE","LEMOYNE":"FALSE","YORK":"TRUE","brand":"THE SALTY ONE","flavor":"Apple","juiceID":1323},{"FREDERICK":"FALSE","GETTYSBURG":"FALSE","LEMOYNE":"FALSE","YORK":"TRUE","brand":"TRANSISTOR","flavor":"LSD","juiceID":1329},{"FREDERICK":"FALSE","GETTYSBURG":"FALSE","LEMOYNE":"FALSE","YORK":"TRUE","brand":"TWIST","flavor":"Menthol No.1","juiceID":1343},{"FREDERICK":"FALSE","GETTYSBURG":"FALSE","LEMOYNE":"FALSE","YORK":"TRUE","brand":"TWIST","flavor":"Tobacco Gold No 1","juiceID":1353},{"FREDERICK":"FALSE","GETTYSBURG":"FALSE","LEMOYNE":"FALSE","YORK":"TRUE","brand":"TWIST","flavor":"Tobacco Platinum","juiceID":1354},{"FREDERICK":"FALSE","GETTYSBURG":"FALSE","LEMOYNE":"FALSE","YORK":"TRUE","brand":"TWIST","flavor":"Watermelon Madness Iced","juiceID":1355},{"FREDERICK":"FALSE","GETTYSBURG":"FALSE","LEMOYNE":"FALSE","YORK":"TRUE","brand":"TWISTED TONGUE","flavor":"Pina Colada","juiceID":1361},{"FREDERICK":"FALSE","GETTYSBURG":"FALSE","LEMOYNE":"FALSE","YORK":"TRUE","brand":"TWISTED TONGUE","flavor":"Sweet Cereal Milk","juiceID":1363},{"FREDERICK":"FALSE","GETTYSBURG":"FALSE","LEMOYNE":"FALSE","YORK":"TRUE","brand":"VAPETASIA","flavor":"Blueberry Custard","juiceID":1366},{"FREDERICK":"FALSE","GETTYSBURG":"FALSE","LEMOYNE":"FALSE","YORK":"TRUE","brand":"VAPETASIA","flavor":"Strawberry Custard","juiceID":1367},{"FREDERICK":"FALSE","GETTYSBURG":"FALSE","LEMOYNE":"FALSE","YORK":"TRUE","brand":"VAPETASIA","flavor":"Vanilla Custard","juiceID":1368},{"FREDERICK":"TRUE","GETTYSBURG":"TRUE","LEMOYNE":"FALSE","YORK":"TRUE","brand":"PodTest=PodTest","flavor":"goodjuice","juiceID":4396}]